Workbook

Sheet Stack-Planer
A1: Stack-Planer | B1: ="Jetzt "&TEXT(G$89,"0")&" Jahre" | E1: ="Nach Massnahmen "&TEXT(G$90,"0")&" Jahre" | L1: ="Punkte: "&TEXT($A$24,"0")&" Ausgang, "&TEXT($C$24,"0")&" real, "&TEXT($G$24,"0")&" nach den Massnahmen. Rechenweg: Blatt Parameter." | Z1: Natty oder TRT (400-1000 ng/dl)
A2: Oben eintragen, was tatsaechlich laeuft und was das letzte Blutbild sagt. Unten ankreuzen, was bereits eingenommen wird und was dazukommen soll. Die drei Scores rechnen sich in Excel sofort neu, ohne dass das Programm nochmal laufen muss. Es wird nichts gespeichert und nichts an die Auswertung zurueckgemeldet. | Z2: TRT plus (1000-1400 ng/dl)
A3: KEINE THERAPIEEMPFEHLUNG. Ein Rechenmodell aus durchschnittlichen Studieneffekten, mehr nicht. Was in einen konkreten Stack gehoert, gehoert mit einem Arzt und einem erfahrenen Coach besprochen. | Z3: Blast moderat (250-350 mg/Woche)
A4: AUSGANGSWERT 80: diese Mappe kennt keine DNA-Auswertung, deshalb wird eine durchschnittliche Anlage unterstellt - jede Kategorie sitzt auf demselben Index. Im Auslieferungszustand (nichts gemessen, Natty oder TRT, keine Orale, nichts angehakt) stehen deshalb genau 80 Punkte da. Wer alle sieben Blutwerte im gruenen Band eintraegt, landet darueber; wer Load, Orale oder schlechte Werte eintraegt, darunter. Mit einer echten DNA-Auswertung steht an dieser Stelle der persoenliche Wert, und die Maluspunkte verteilen sich ungleich auf die Kategorien statt gleichmaessig. KEINE THERAPIEEMPFEHLUNG - Stacks gehoeren mit Arzt und Coach besprochen. | Z4: Blast fortgeschritten (500-750 mg/Woche)
A5: 1. Was laeuft | Z5: Blast Profi (1 g und mehr)
A6: Gesamt-Load | C6: Natty oder TRT (400-1000 ng/dl) | G6: Hebt die Maluspunkte in allen Kategorien OHNE eigenen Blutwert. Wo gemessen wurde, steckt die Dosis bereits im Wert.
A7: Anwendungsart | C7: Dauerblast (durchgehend) | G7: Blast and Cruise zaehlt nur als solches, wenn die Pause so lang ist wie der Block (Time On = Time Off, dazwischen echtes TRT). Alles andere ist Dauerblast mit Zwischenstopps - dann die erste Option waehlen. Ab Natty/TRT ohne Wirkung, weil es dort keinen Ueberschuss zu daempfen gibt. | Z7: Dauerblast (durchgehend)
A8: Geplante Anwendungsdauer | C8: 15 Jahre | G8: So viele Jahre laeuft die Last. Sie aendert den Score NICHT - der sagt, wie hart gerade gefahren wird. Sie aendert das Endalter: jedes Jahr unter Last kostet einzeln, und zwar umso mehr, je aelter man in diesem Jahr ist. Die letzte Stufe hat kein Ende - da laeuft die Uhr, bis das Budget leer ist. | Z8: Blast and Cruise (Time On = Time Off)
A9: Alter (Jahre) | C9: 30 | G9: =" Daraus: "&IF(G$87>900,"Last ohne Ausstieg",TEXT(G$87,"0")&" Jahre unter Last")&". Ein Lebensjahr kostet in diesem Alter das "&TEXT(Parameter!$D$120,"0.00")&"-fache, unter diesem Stack das "&TEXT(Parameter!$D$123*Parameter!$D$120,"0.00")&"-fache. Das Endalter steht oben in der "&"angehefteten Zeile."
Z10: <5 Jahre
A11: 2. Aktuelle Blutwerte | Z11: 10 Jahre
A12: Leer lassen, was nicht gemessen ist - dann rechnet das Blatt fuer diese Kategorie mit der Genetik weiter. Ein eingetragener Wert zaehlt zu 75 Prozent, die Anlage bleibt mit 25 Prozent stehen: eine einzelne Messung ist eine Momentaufnahme. Wo ein guter Wert steht, hat die passende Massnahme nichts mehr zu holen - genau so soll es sein. | Z12: 15 Jahre
A13: Wert | C13: Eingabe | G13: Baender (gut / mittel / schlecht) | O13: Hinweis | Z13: bis dass der Tod uns scheidet
A14: Blutdruck systolisch (mmHg) | G14: unter 115 / 115 bis 125 / 125 bis 140 / ab 140 | O14: In Ruhe und an mehreren Tagen gemessen, nicht direkt nach dem Training. Das Risiko steigt in den grossen Kohorten durchgehend ab 115/75 mmHg - es gibt keinen Sockel, unterhalb dessen es egal waere, deshalb liegt das Optimum unter 115. Die ESC nennt ab 120 erhoeht und ab 140 Bluthochdruck; ab 140 steht hier der Endlevel, weil dort gehandelt werden muss und nicht erst bei Grad 2 (160).
A15: Haematokrit (%) | G15: unter 45 / 45 bis 50 / 50 bis 54 / ueber 54 | O15: Der Wert, wegen dem die Blutspende auf dem Plan steht. 45 und 48 sind nicht dasselbe: die Blutviskositaet steigt oberhalb von rund 45 Prozent ueberproportional, und schon innerhalb des Normbereichs haben die oberen Quartile mehr Thrombosen und Herzereignisse. Deshalb liegt das Optimum unter 45, auch wenn 52 offiziell noch normal ist. Ab 48 wuerde kein Arzt eine Testosterontherapie neu beginnen, ueber 54 heisst es in der Leitlinie: Dosis runter, absetzen oder Aderlass. Nach unten hat der Wert eine Grenze, die das Modell nicht kennt - unter 38 wird es Blutarmut. | Z15: nicht gemessen
A16: LDL-Cholesterin (mmol/l) | G16: unter 1,4 (55 mg/dl) / 1,4 bis 2,6 (55-100 mg/dl) / 2,6 bis 3,4 (100-130 mg/dl) / ueber 3,4 (ueber 130 mg/dl) | O16: Das Optimum ist der ESC/EAS-Zielwert fuer SEHR hohes Risiko: unter 1,4 mmol/l (55 mg/dl). Genau dort steht ein langjaehriger Nutzer, und eine untere Schwelle, ab der es nicht mehr besser wird, ist bis heute nicht gefunden worden - ein Neugeborenes hat rund 30 mg/dl. 1,8 (70 mg/dl) ist die Behandlungsschwelle bei hohem Risiko, kein Optimum. Der Endlevel liegt bei 3,4 (130 mg/dl), nicht erst bei 4,1 (160): 160 ist die Marke fuer eine manifeste Hypercholesterinaemie, und als Alarm ist das zu spaet. Hier bringt ein Statin am meisten. | Z16: unter 115
A17: HDL-Cholesterin (mmol/l) | G17: ueber 1,3 (50 mg/dl) / 1,0 bis 1,3 (39-50 mg/dl) / 0,6 bis 1,0 (23-39 mg/dl) / unter 0,6 (unter 23 mg/dl) | O17: ACHTUNG umgekehrte Richtung: hier ist HOCH gut. Unter 1,0 mmol/l (40 mg/dl) gilt beim Mann als erniedrigt, aber der Risikoabfall geht bis rund 1,5 (60 mg/dl) weiter - deshalb liegt das Optimum ueber 1,3 (50 mg/dl) und nicht knapp ueber der Grenze zum Krankhaften. Der Endlevel liegt bei 0,6 (23 mg/dl): wer bei 0,4 ankommt, braucht keine Warnung mehr. Sehr hohe Werte ueber 2,3 (90 mg/dl) sind uebrigens auch nicht besser, aber das ist nicht das Problem dieser Gruppe. | Z17: 115 bis 125
A18: Triglyzeride (mmol/l) | G18: unter 1,0 (89 mg/dl) / 1,0 bis 1,7 (89-150 mg/dl) / 1,7 bis 3,4 (150-300 mg/dl) / ueber 3,4 (ueber 300 mg/dl) | O18: Nuechtern gemessen, sonst ist der Wert wertlos. 1,7 mmol/l (150 mg/dl) heisst nur noch normal; das Optimum liegt unter 1,0 (89 mg/dl), und dort sitzen auch die Leute mit der besten Insulinlage. Der Endlevel steht bei 3,4 (300 mg/dl) - die 5,6 (500 mg/dl), ab denen die Bauchspeicheldruese gefaehrdet ist, sind der Notfall, und ein Notfall ist keine Warnung mehr. | Z18: 125 bis 140
A19: Nuechternglukose (mg/dl) | G19: unter 80 (4,4 mmol/l) / 80 bis 95 (4,4-5,3 mmol/l) / 95 bis 110 (5,3-6,1 mmol/l) / ab 110 (ab 6,1 mmol/l) | O19: Nuechtern heisst acht Stunden nichts gegessen. Der Risikoanstieg beginnt in den Kohorten deutlich vor 100 mg/dl, also vor der offiziellen Praediabetesgrenze - deshalb liegt das Optimum unter 80. Nach ADA ist 100 bis 125 mg/dl Praediabetes und ab 126 Diabetes; der Endlevel steht hier schon bei 110, wo die WHO von einer gestoerten Nuechternglukose spricht. Eine Warnung, die auf die Diagnose wartet, ist keine mehr. Alternativ HbA1c: unter 5,0 / 5,0 bis 5,4 / 5,4 bis 5,8 / ab 5,8 Prozent. | Z19: ab 140
A20: Cystatin C (mg/l oder Kreatinin-eGFR) | G20: unter 0,80 (eGFR ueber 110) / 0,80 bis 1,00 (eGFR 85-110) / 1,00 bis 1,30 (eGFR 60-85) / ueber 1,30 (eGFR unter 60) | O20: Besser als Kreatinin, weil unabhaengig von der Muskelmasse - bei Kraftsportlern ist Kreatinin systematisch zu hoch. Die Klammerwerte sind die eGFR nach CKD-EPI fuer einen 40-jaehrigen Mann. Der Normbereich reicht bis 1,0, aber Sterblichkeit und Herzereignisse steigen schon innerhalb davon - deshalb liegt das Optimum unter 0,80. Der Endlevel steht bei 1,30, also bei eGFR 60: das ist die Grenze zur chronischen Nierenerkrankung und nicht erst Stadium G3b. WENN DU KEIN CYSTATIN C HAST: nimm die eGFR aus dem Kreatinin und ordne sie nach den Klammerwerten ein - ungenau ist besser als gar nichts. Sie faellt bei viel Muskel aber systematisch zu schlecht aus, weil Kreatinin aus dem Muskel kommt. Sieht sie schlecht aus, lass Cystatin C nachbestimmen, bevor aus einer Muskelmasse eine Nierenerkrankung wird.
Z21: nicht gemessen
A22: 3. Ergebnis | Z22: unter 45
A23: Ausgangswert (Durchschnitt) | C23: Real (Blutwerte + Load + was laeuft) | G23: Nach den geplanten Massnahmen | O23: Rechnet Excel selbst. Die drei Zahlen sind dieselbe Skala wie im DNA-Bericht: 100 waere kein einziger Negativpunkt. Der Unterschied zwischen der ersten und der zweiten Zahl ist alles, was an Dosis, Blutwerten und Medikation zusammenkommt - Dosis, Blutwerte, Medikation. Der Unterschied zwischen der zweiten und der dritten ist das, was noch zu holen ist. ACHTUNG: die Punkte sind KEIN Mittelwert ueber die Systeme. Jedes System wird einzeln bewertet, und ein System am Anschlag zieht die Zahl nach unten, auch wenn alle anderen gruen sind - die Kette reisst am schwaechsten Glied. Welches das ist, steht auf dem Block Systeme weiter unten. | Z23: 45 bis 50
A24: 80 | C24: =Parameter!$D$91 | G24: =Parameter!$D$92 | Z24: 50 bis 54
A25: Durchschnittliche Anlage, ohne Orale, ohne Blutwerte, ohne Medikation. Ein individueller Wert steht nur im DNA-Bericht. | C25: Wo gemessen wurde, zaehlt die Messung zu 75 Prozent. Aufschluesselung je System: Block Systeme weiter unten. | G25: Erst real, wenn die Zielwerte rechts erreicht werden. | Z25: ueber 54
A27: 4. Was laeuft, was geplant ist | Z27: nicht gemessen
A28: LAEUFT BEREITS zaehlt nur in Kategorien OHNE Blutwert - wo gemessen wurde, steckt die Wirkung schon im Messwert und ein zweites Mal gutschreiben waere doppelt gezaehlt. GEPLANT zaehlt ueberall, aber gedaempft nach dem Messwert: gruenes Band 0 Prozent, mittleres Band 50, rotes Band 100. Ein Statin bei LDL unter 1,7 bringt in dieser Kategorie also nichts mehr, und der Weg von 2,5 auf 1,7 zaehlt nur halb - die gefaehrliche Strecke liegt weiter oben. Schaedliche Faktoren werden NICHT gedaempft: ein SGLT2-Hemmer hebt den Haematokrit auch dann, wenn er gerade gut ist. | Z28: unter 1,4 (55 mg/dl)
A29: WAS NUR SCHADET steht unten und ist durchgehend rot hinterlegt - sie haben in diesem Modell keinen einzigen Gesundheitsnutzen. Fuer sie sind beide Ankreuzspalten gleichwertig: ob eine Substanz schon laeuft oder erst geplant ist, aendert nichts daran, was sie anrichtet, und gedaempft wird sie nie. TESTOSTERON hat bewusst keine Faktoren - es ist die Grundlast und steckt bereits im Gesamt-Load oben. Alle anderen Zeilen zeigen, was sie ZUSAETZLICH zu Testosteron auf einzelne Systeme legen. Die 17-alpha-alkylierten Oralen stehen hier einzeln mit ihren eigenen Leber-, LDL- und HDL-Faktoren - einen Sammelschalter oben gibt es nicht mehr. | Z29: 1,4 bis 2,6 (55-100 mg/dl)
A30: Achtung beim Lesen: gedaempft wird je Kategorie, nicht je Substanz. Ein Statin bei perfektem LDL kann trotzdem noch einen kleinen Gewinn zeigen - der kommt dann aus 'Gefaesse/Atherosklerose', und fuer diese Kategorie gibt es in der Liste oben keinen Blutwert. Dasselbe beim Sartan ueber den Herzmuskel. Wer das ausschliessen will, muss diese Kategorien ueber Bildgebung beurteilen lassen - ein Blutbild sagt dazu nichts. | Z30: 2,6 bis 3,4 (100-130 mg/dl)
A31: HANDLUNGSPLAN - sortiert sich selbst. Gerechnet wird, was mit dem Score passiert, wenn NUR diese eine Massnahme dazukommt, bei den Blutwerten und dem Stack, die oben stehen. Wer einen hohen Haematokrit eintraegt, findet den Aderlass hier ganz oben; wer einen guten eintraegt, findet ihn gar nicht mehr. Je Wirkstoffklasse steht nur der Beste da - Sartan und ACE-Hemmer sind dieselbe Massnahme, nicht zwei; die schwaechere steht als Alternative dahinter. Was schon laeuft oder schon geplant ist, wird nicht noch einmal vorgeschlagen, und alles andere wird gegen den Stand NACH den geplanten Massnahmen gerechnet - hakt man das Statin an, faellt der PCSK9-Hemmer sofort weg statt unveraendert stehen zu bleiben. Dieselbe Zahl steht in der Spalte 'bringt' bei jeder Substanz. | Z31: ueber 3,4 (ueber 130 mg/dl)
A32: =IFERROR(IF(LARGE($AC$40:$AC$81,1)<=0.05,"",1&". "&INDEX($A$40:$A$81,MATCH(LARGE($AC$40:$AC$81,1),$AC$40:$AC$81,0))&" ["&INDEX($D$40:$D$81,MATCH(LARGE($AC$40:$AC$81,1),$AC$40:$AC$81,0))&"]"&IF(SUMPRODUCT(($D$40:$D$81=INDEX($D$40:$D$81,MATCH(LARGE($AC$40:$AC$81,1),$AC$40:$AC$81,0)))*($AB$40:$AB$81=2)*($AA$40:$AA$81>0)*ROW($A$40:$A$81))=0,""," Alternative: "&INDEX($A$40:$A$81,SUMPRODUCT(($D$40:$D$81=INDEX($D$40:$D$81,MATCH(LARGE($AC$40:$AC$81,1),$AC$40:$AC$81,0)))*($AB$40:$AB$81=2)*($AA$40:$AA$81>0)*ROW($A$40:$A$81))-40+1))),"") | F32: =IFERROR(IF(LARGE($AC$40:$AC$81,1)<=0.05,"",TEXT(INDEX($F$40:$F$81,MATCH(LARGE($AC$40:$AC$81,1),$AC$40:$AC$81,0)),"+0.0")&" Punkte"),"")
A33: =IFERROR(IF(LARGE($AC$40:$AC$81,2)<=0.05,"",2&". "&INDEX($A$40:$A$81,MATCH(LARGE($AC$40:$AC$81,2),$AC$40:$AC$81,0))&" ["&INDEX($D$40:$D$81,MATCH(LARGE($AC$40:$AC$81,2),$AC$40:$AC$81,0))&"]"&IF(SUMPRODUCT(($D$40:$D$81=INDEX($D$40:$D$81,MATCH(LARGE($AC$40:$AC$81,2),$AC$40:$AC$81,0)))*($AB$40:$AB$81=2)*($AA$40:$AA$81>0)*ROW($A$40:$A$81))=0,""," Alternative: "&INDEX($A$40:$A$81,SUMPRODUCT(($D$40:$D$81=INDEX($D$40:$D$81,MATCH(LARGE($AC$40:$AC$81,2),$AC$40:$AC$81,0)))*($AB$40:$AB$81=2)*($AA$40:$AA$81>0)*ROW($A$40:$A$81))-40+1))),"") | F33: =IFERROR(IF(LARGE($AC$40:$AC$81,2)<=0.05,"",TEXT(INDEX($F$40:$F$81,MATCH(LARGE($AC$40:$AC$81,2),$AC$40:$AC$81,0)),"+0.0")&" Punkte"),"") | Z33: nicht gemessen
A34: =IFERROR(IF(LARGE($AC$40:$AC$81,3)<=0.05,"",3&". "&INDEX($A$40:$A$81,MATCH(LARGE($AC$40:$AC$81,3),$AC$40:$AC$81,0))&" ["&INDEX($D$40:$D$81,MATCH(LARGE($AC$40:$AC$81,3),$AC$40:$AC$81,0))&"]"&IF(SUMPRODUCT(($D$40:$D$81=INDEX($D$40:$D$81,MATCH(LARGE($AC$40:$AC$81,3),$AC$40:$AC$81,0)))*($AB$40:$AB$81=2)*($AA$40:$AA$81>0)*ROW($A$40:$A$81))=0,""," Alternative: "&INDEX($A$40:$A$81,SUMPRODUCT(($D$40:$D$81=INDEX($D$40:$D$81,MATCH(LARGE($AC$40:$AC$81,3),$AC$40:$AC$81,0)))*($AB$40:$AB$81=2)*($AA$40:$AA$81>0)*ROW($A$40:$A$81))-40+1))),"") | F34: =IFERROR(IF(LARGE($AC$40:$AC$81,3)<=0.05,"",TEXT(INDEX($F$40:$F$81,MATCH(LARGE($AC$40:$AC$81,3),$AC$40:$AC$81,0)),"+0.0")&" Punkte"),"") | Z34: ueber 1,3 (50 mg/dl)
A35: =IFERROR(IF(LARGE($AC$40:$AC$81,4)<=0.05,"",4&". "&INDEX($A$40:$A$81,MATCH(LARGE($AC$40:$AC$81,4),$AC$40:$AC$81,0))&" ["&INDEX($D$40:$D$81,MATCH(LARGE($AC$40:$AC$81,4),$AC$40:$AC$81,0))&"]"&IF(SUMPRODUCT(($D$40:$D$81=INDEX($D$40:$D$81,MATCH(LARGE($AC$40:$AC$81,4),$AC$40:$AC$81,0)))*($AB$40:$AB$81=2)*($AA$40:$AA$81>0)*ROW($A$40:$A$81))=0,""," Alternative: "&INDEX($A$40:$A$81,SUMPRODUCT(($D$40:$D$81=INDEX($D$40:$D$81,MATCH(LARGE($AC$40:$AC$81,4),$AC$40:$AC$81,0)))*($AB$40:$AB$81=2)*($AA$40:$AA$81>0)*ROW($A$40:$A$81))-40+1))),"") | F35: =IFERROR(IF(LARGE($AC$40:$AC$81,4)<=0.05,"",TEXT(INDEX($F$40:$F$81,MATCH(LARGE($AC$40:$AC$81,4),$AC$40:$AC$81,0)),"+0.0")&" Punkte"),"") | Z35: 1,0 bis 1,3 (39-50 mg/dl)
A36: =IFERROR(IF(LARGE($AC$40:$AC$81,5)<=0.05,"",5&". "&INDEX($A$40:$A$81,MATCH(LARGE($AC$40:$AC$81,5),$AC$40:$AC$81,0))&" ["&INDEX($D$40:$D$81,MATCH(LARGE($AC$40:$AC$81,5),$AC$40:$AC$81,0))&"]"&IF(SUMPRODUCT(($D$40:$D$81=INDEX($D$40:$D$81,MATCH(LARGE($AC$40:$AC$81,5),$AC$40:$AC$81,0)))*($AB$40:$AB$81=2)*($AA$40:$AA$81>0)*ROW($A$40:$A$81))=0,""," Alternative: "&INDEX($A$40:$A$81,SUMPRODUCT(($D$40:$D$81=INDEX($D$40:$D$81,MATCH(LARGE($AC$40:$AC$81,5),$AC$40:$AC$81,0)))*($AB$40:$AB$81=2)*($AA$40:$AA$81>0)*ROW($A$40:$A$81))-40+1))),"") | F36: =IFERROR(IF(LARGE($AC$40:$AC$81,5)<=0.05,"",TEXT(INDEX($F$40:$F$81,MATCH(LARGE($AC$40:$AC$81,5),$AC$40:$AC$81,0)),"+0.0")&" Punkte"),"") | Z36: 0,6 bis 1,0 (23-39 mg/dl)
A37: =IFERROR(IF(LARGE($AC$40:$AC$81,6)<=0.05,"",6&". "&INDEX($A$40:$A$81,MATCH(LARGE($AC$40:$AC$81,6),$AC$40:$AC$81,0))&" ["&INDEX($D$40:$D$81,MATCH(LARGE($AC$40:$AC$81,6),$AC$40:$AC$81,0))&"]"&IF(SUMPRODUCT(($D$40:$D$81=INDEX($D$40:$D$81,MATCH(LARGE($AC$40:$AC$81,6),$AC$40:$AC$81,0)))*($AB$40:$AB$81=2)*($AA$40:$AA$81>0)*ROW($A$40:$A$81))=0,""," Alternative: "&INDEX($A$40:$A$81,SUMPRODUCT(($D$40:$D$81=INDEX($D$40:$D$81,MATCH(LARGE($AC$40:$AC$81,6),$AC$40:$AC$81,0)))*($AB$40:$AB$81=2)*($AA$40:$AA$81>0)*ROW($A$40:$A$81))-40+1))),"") | F37: =IFERROR(IF(LARGE($AC$40:$AC$81,6)<=0.05,"",TEXT(INDEX($F$40:$F$81,MATCH(LARGE($AC$40:$AC$81,6),$AC$40:$AC$81,0)),"+0.0")&" Punkte"),"") | Z37: unter 0,6 (unter 23 mg/dl)
A39: Substanz | B39: laeuft bereits | C39: geplant | D39: Wirkstoffklasse | E39: Evidenz | F39: bringt | G39: Haematokrit | H39: HDL | I39: LDL | J39: Blutdruck | K39: Herzmuskel | L39: Gefaesse | M39: Thrombose | N39: Psyche | O39: Aorta/Lunge | P39: Triglyzeride | Q39: Rhythmus | R39: Niere | S39: Leber allg. | T39: Glukose | U39: Lp(a) | V39: E2 | W39: Punkte gibt es erst, wenn | X39: Anmerkung | Z39: nicht gemessen
A40: PCSK9-Hemmer oder Inclisiran | D40: Statin/PCSK9 | E40: A | F40: =IF(OR($B40="x",$C40="x"),"",MAX(0,Parameter!$B$36/(((SUM(G328:V328)+SUM(G331:V331))^(1/Parameter!$B$40))*Parameter!$D$88)^(1/Parameter!$B$38)-Parameter!$D$92)) | I40: =Parameter!E258 | L40: =Parameter!I258 | U40: =Parameter!H258 | W40: LDL unter 1,4 mmol/l. Lp(a) sinkt nur um 20 bis 25 Prozent - ein hoher Ausgangswert bleibt auch danach hoch. | X40: PCSK9-Hemmer senken zusaetzlich Lp(a) - das kann sonst nichts auf diesem Blatt. Wegen der Kosten werden sie aber nur an Statin-Nonresponder oder bei Unvertraeglichkeit verschrieben; rund 95 Prozent bekommen ein Statin und sonst nichts. Deshalb steht der PCSK9-Hemmer hier in derselben Klasse wie das Statin: Es zaehlt der staerkere von beiden, nicht beide zusammen. BESONDERHEIT: derzeit das einzige Mittel, das Lp(a) ueberhaupt senkt. KOPPLUNG: die Lp(a)-Wirkung ist entkoppelt, weil es fuer Lp(a) keinen Eingabewert gibt - sie bleibt also immer voll stehen. | Z40: unter 1,0 (89 mg/dl) | AA40: =IF(N(F40)=0,0,F40-ROW()/1000000) | AB40: =SUMPRODUCT(($D$40:$D$81=$D40)*($AA$40:$AA$81>AA40))+1 | AC40: =IF(AA40<=0,0,IF(AB40=1,AA40,0))
A41: Statin | D41: Statin/PCSK9 | E41: A | F41: =IF(OR($B41="x",$C41="x"),"",MAX(0,Parameter!$B$36/(((SUM(G328:V328)+SUM(G332:V332))^(1/Parameter!$B$40))*Parameter!$D$88)^(1/Parameter!$B$38)-Parameter!$D$92)) | I41: =Parameter!E255 | L41: =Parameter!I255 | T41: =Parameter!T255 | W41: LDL unter 1,8 mmol/l (70 mg/dl). Non-Responder gibt es wirklich - ohne Kontrollwert nach 6 bis 8 Wochen sind diese Punkte nur eine Annahme. | X41: BESONDERHEITEN: Rosuvastatin und Atorvastatin sind die potentesten, Pravastatin das vertraeglichste bei Muskelproblemen, Simvastatin das mit dem hoechsten Myopathierisiko. Monacolin K aus rotem Reis IST Lovastatin - nie zusaetzlich zu einem verschriebenen Statin. KOPPLUNG: auch der Plaque-Nutzen haengt am LDL, nur rund 10 Prozent laufen ueber die pleiotropen Effekte. Bei LDL unter 1,7 bringt ein Statin deshalb praktisch nichts mehr. | Z41: 1,0 bis 1,7 (89-150 mg/dl) | AA41: =IF(N(F41)=0,0,F41-ROW()/1000000) | AB41: =SUMPRODUCT(($D$40:$D$81=$D41)*($AA$40:$AA$81>AA41))+1 | AC41: =IF(AA41<=0,0,IF(AB41=1,AA41,0))
A42: Ezetimib | D42: Cholesterin-Resorptionshemmer | E42: A | F42: =IF(OR($B42="x",$C42="x"),"",MAX(0,Parameter!$B$36/(((SUM(G328:V328)+SUM(G333:V333))^(1/Parameter!$B$40))*Parameter!$D$88)^(1/Parameter!$B$38)-Parameter!$D$92)) | I42: =Parameter!E256 | L42: =Parameter!I256 | W42: LDL unter 1,8 mmol/l, meist erst zusammen mit einem Statin erreichbar. | X42: Rund 20 Prozent LDL-Senkung auf der Aufnahmeseite statt der Syntheseseite. KOPPLUNG: wirkt ausschliesslich ueber das LDL, deshalb Rest 0 in beiden Kategorien - IMPROVE-IT zeigte den Nutzen exakt proportional zur erreichten LDL-Senkung. | Z42: 1,7 bis 3,4 (150-300 mg/dl) | AA42: =IF(N(F42)=0,0,F42-ROW()/1000000) | AB42: =SUMPRODUCT(($D$40:$D$81=$D42)*($AA$40:$AA$81>AA42))+1 | AC42: =IF(AA42<=0,0,IF(AB42=1,AA42,0))
A43: Bempedoinsaeure | D43: ACL-Hemmer | E43: B | F43: =IF(OR($B43="x",$C43="x"),"",MAX(0,Parameter!$B$36/(((SUM(G328:V328)+SUM(G334:V334))^(1/Parameter!$B$40))*Parameter!$D$88)^(1/Parameter!$B$38)-Parameter!$D$92)) | I43: =Parameter!E257 | L43: =Parameter!I257 | W43: LDL unter 1,8 mmol/l. | X43: BESONDERHEIT: wird erst in der Leber aktiviert und erreicht den Muskel praktisch nicht. Damit faellt die Myopathie weg - fuer jemanden, der schwer trainiert, der eigentliche Punkt gegenueber dem Statin. | Z43: ueber 3,4 (ueber 300 mg/dl) | AA43: =IF(N(F43)=0,0,F43-ROW()/1000000) | AB43: =SUMPRODUCT(($D$40:$D$81=$D43)*($AA$40:$AA$81>AA43))+1 | AC43: =IF(AA43<=0,0,IF(AB43=1,AA43,0))
A44: Sartan (ARB) | D44: RAAS-Blocker | E44: A | F44: =IF(OR($B44="x",$C44="x"),"",MAX(0,Parameter!$B$36/(((SUM(G328:V328)+SUM(G335:V335))^(1/Parameter!$B$40))*Parameter!$D$88)^(1/Parameter!$B$38)-Parameter!$D$92)) | J44: =Parameter!D259 | K44: =Parameter!M259 | O44: =Parameter!J259 | R44: =Parameter!Q259 | W44: Blutdruck unter 130/80 in Ruhe, an mehreren Tagen gemessen, nicht direkt nach dem Training. | X44: BESONDERHEIT TELMISARTAN: partielle PPAR-gamma-Aktivitaet, daher ein kleiner Stoffwechselbonus, den die anderen Sartane nicht haben, dazu 24 Stunden Wirkdauer. KOPPLUNG: am Herzmuskel bleibt die Haelfte auch bei gutem Blutdruck stehen - die Massenreduktion geht nachweislich ueber den reinen Druckeffekt hinaus. Die Niere ist ganz entkoppelt, die Nierenprotektion haengt nicht am Ausgangsdruck. | AA44: =IF(N(F44)=0,0,F44-ROW()/1000000) | AB44: =SUMPRODUCT(($D$40:$D$81=$D44)*($AA$40:$AA$81>AA44))+1 | AC44: =IF(AA44<=0,0,IF(AB44=1,AA44,0))
A45: ACE-Hemmer | D45: RAAS-Blocker | E45: A | F45: =IF(OR($B45="x",$C45="x"),"",MAX(0,Parameter!$B$36/(((SUM(G328:V328)+SUM(G336:V336))^(1/Parameter!$B$40))*Parameter!$D$88)^(1/Parameter!$B$38)-Parameter!$D$92)) | J45: =Parameter!D260 | K45: =Parameter!M260 | O45: =Parameter!J260 | R45: =Parameter!Q260 | W45: Blutdruck unter 130/80 in Ruhe. | X45: Gleiche Kaskade wie das Sartan, eine Stufe frueher. Reizhusten ist der haeufigste Wechselgrund. ZUR NIERE: ACE-Hemmer sind entgegen einer verbreiteten Annahme genauso nierenprotektiv wie Sartane - das ist eine der am besten belegten Indikationen ueberhaupt (Captopril-Studie, REIN, AIPRI), und die Leitlinien fuehren beide Klassen dafuer gleichwertig. Der Unterschied liegt bei Husten und Angiooedem, nicht an der Niere. Deshalb hier dieselben Werte wie beim Sartan. | Z45: nicht gemessen | AA45: =IF(N(F45)=0,0,F45-ROW()/1000000) | AB45: =SUMPRODUCT(($D$40:$D$81=$D45)*($AA$40:$AA$81>AA45))+1 | AC45: =IF(AA45<=0,0,IF(AB45=1,AA45,0))
A46: Amlodipin (Calciumantagonist) | D46: Calciumantagonist | E46: A | F46: =IF(OR($B46="x",$C46="x"),"",MAX(0,Parameter!$B$36/(((SUM(G328:V328)+SUM(G337:V337))^(1/Parameter!$B$40))*Parameter!$D$88)^(1/Parameter!$B$38)-Parameter!$D$92)) | J46: =Parameter!D261 | K46: =Parameter!M261 | L46: =Parameter!I261 | O46: =Parameter!J261 | W46: Blutdruck unter 130/80 in Ruhe. | X46: Senkt zentralen Druck und Gefaesssteifigkeit, entlastet also die Aortenwand. ACHTUNG BEI BINDEGEWEBSSCHWAECHE: bei Marfan gibt es Daten, nach denen Calciumantagonisten Aneurysma und Dissektion eher verschlechtern. Wer eine bekannte Bindegewebserkrankung oder eine erweiterte Aortenwurzel hat, klaert das vor der Einnahme ab. | Z46: unter 80 (4,4 mmol/l) | AA46: =IF(N(F46)=0,0,F46-ROW()/1000000) | AB46: =SUMPRODUCT(($D$40:$D$81=$D46)*($AA$40:$AA$81>AA46))+1 | AC46: =IF(AA46<=0,0,IF(AB46=1,AA46,0))
A47: Nebivolol (Betablocker) | D47: Betablocker | E47: B | F47: =IF(OR($B47="x",$C47="x"),"",MAX(0,Parameter!$B$36/(((SUM(G328:V328)+SUM(G338:V338))^(1/Parameter!$B$40))*Parameter!$D$88)^(1/Parameter!$B$38)-Parameter!$D$92)) | J47: =Parameter!D262 | K47: =Parameter!M262 | O47: =Parameter!J262 | Q47: =Parameter!L262 | W47: Blutdruck unter 130/80, Ruhepuls im Zielbereich. | X47: Der Betablocker mit NO-vermittelter Gefaesserweiterung und dem geringsten Einfluss auf die Blutfette. KOPPLUNG: die Rhythmuswirkung ist entkoppelt - die Frequenzkontrolle haengt nicht am Ausgangsblutdruck. | Z47: 80 bis 95 (4,4-5,3 mmol/l) | AA47: =IF(N(F47)=0,0,F47-ROW()/1000000) | AB47: =SUMPRODUCT(($D$40:$D$81=$D47)*($AA$40:$AA$81>AA47))+1 | AC47: =IF(AA47<=0,0,IF(AB47=1,AA47,0))
A48: Tadalafil niedrig dosiert | D48: PDE5-Hemmer | E48: C | F48: =IF(OR($B48="x",$C48="x"),"",MAX(0,Parameter!$B$36/(((SUM(G328:V328)+SUM(G339:V339))^(1/Parameter!$B$40))*Parameter!$D$88)^(1/Parameter!$B$38)-Parameter!$D$92)) | J48: =Parameter!D263 | K48: =Parameter!M263 | L48: =Parameter!I263 | W48: Blutdruck unter 130/80. Als alleinige Massnahme reicht es dafuer selten. | X48: Taeglich niedrig dosiert verbessert es die Endothelfunktion und senkt den Blutdruck leicht. Die Daten zur Hypertrophie stammen aus kleinen Studien, daher Stufe C. | Z48: 95 bis 110 (5,3-6,1 mmol/l) | AA48: =IF(N(F48)=0,0,F48-ROW()/1000000) | AB48: =SUMPRODUCT(($D$40:$D$81=$D48)*($AA$40:$AA$81>AA48))+1 | AC48: =IF(AA48<=0,0,IF(AB48=1,AA48,0))
A49: Blutspende oder Aderlass | D49: Aderlass | E49: B | F49: =IF(OR($B49="x",$C49="x"),"",MAX(0,Parameter!$B$36/(((SUM(G328:V328)+SUM(G340:V340))^(1/Parameter!$B$40))*Parameter!$D$88)^(1/Parameter!$B$38)-Parameter!$D$92)) | G49: =Parameter!O264 | W49: Haematokrit unter 47 Prozent, dabei Ferritin nicht unter 30. | X49: Die direkteste und billigste Massnahme ueberhaupt. KOPPLUNG: Rest 0 - bei einem Haematokrit von 44 gibt es schlicht nichts abzulassen. | Z49: ab 110 (ab 6,1 mmol/l) | AA49: =IF(N(F49)=0,0,F49-ROW()/1000000) | AB49: =SUMPRODUCT(($D$40:$D$81=$D49)*($AA$40:$AA$81>AA49))+1 | AC49: =IF(AA49<=0,0,IF(AB49=1,AA49,0))
A50: SGLT2-Hemmer | D50: SGLT2 | E50: A | F50: =IF(OR($B50="x",$C50="x"),"",MAX(0,Parameter!$B$36/(((SUM(G328:V328)+SUM(G341:V341))^(1/Parameter!$B$40))*Parameter!$D$88)^(1/Parameter!$B$38)-Parameter!$D$92)) | G50: =Parameter!O265 | J50: =Parameter!D265 | K50: =Parameter!M265 | R50: =Parameter!Q265 | T50: =Parameter!T265 | W50: Nuechternglukose unter 93 mg/dl bzw. HbA1c unter 5,7. Haematokrit gegenchecken, er steigt unter SGLT2. | X50: BESONDERHEIT: hebt den Haematokrit um 2 bis 4 Prozentpunkte - auf Kur die falsche Richtung, deshalb die Minuszeile. KOPPLUNG: Niere und Herzmuskel sind ENTKOPPELT. Der Nutzen bei Herzinsuffizienz und Nierenerkrankung ist in DAPA-HF, EMPEROR, DAPA-CKD und EMPA-KIDNEY auch bei Menschen ohne Diabetes belegt - er haengt also nicht am Blutzucker. Nur die Glukosewirkung selbst ist gekoppelt. | AA50: =IF(N(F50)=0,0,F50-ROW()/1000000) | AB50: =SUMPRODUCT(($D$40:$D$81=$D50)*($AA$40:$AA$81>AA50))+1 | AC50: =IF(AA50<=0,0,IF(AB50=1,AA50,0))
A51: GLP-1- oder GLP-1/GIP-Agonist | D51: Inkretin | E51: A | F51: =IF(OR($B51="x",$C51="x"),"",MAX(0,Parameter!$B$36/(((SUM(G328:V328)+SUM(G342:V342))^(1/Parameter!$B$40))*Parameter!$D$88)^(1/Parameter!$B$38)-Parameter!$D$92)) | H51: =Parameter!F266 | J51: =Parameter!D266 | L51: =Parameter!I266 | P51: =Parameter!G266 | S51: =Parameter!R266 | T51: =Parameter!T266 | W51: Nuechternglukose unter 93 mg/dl, Triglyzeride unter 1,2 mmol/l. | X51: BESONDERHEITEN: Tirzepatid staerker als Semaglutid, Retatrutid nochmal staerker, aber noch nicht zugelassen. Im Defizit geht Magermasse mit runter. KOPPLUNG: bei normalem Blutzucker faellt die Glukosewirkung weg, die Leberwirkung nicht - die Reduktion des Leberfetts laeuft ueber den Gewichtsverlust. Der Gefaessnutzen bleibt zu 60 Prozent stehen, in SELECT profitierten auch Menschen ohne Diabetes. | Z51: nicht gemessen | AA51: =IF(N(F51)=0,0,F51-ROW()/1000000) | AB51: =SUMPRODUCT(($D$40:$D$81=$D51)*($AA$40:$AA$81>AA51))+1 | AC51: =IF(AA51<=0,0,IF(AB51=1,AA51,0))
A52: Berberin oder Metformin | D52: Insulinsensitizer | E52: B | F52: =IF(OR($B52="x",$C52="x"),"",MAX(0,Parameter!$B$36/(((SUM(G328:V328)+SUM(G343:V343))^(1/Parameter!$B$40))*Parameter!$D$88)^(1/Parameter!$B$38)-Parameter!$D$92)) | I52: =Parameter!E267 | P52: =Parameter!G267 | S52: =Parameter!R267 | T52: =Parameter!T267 | W52: Nuechternglukose unter 93 mg/dl. | X52: BESONDERHEITEN: Berberin ist frei verkaeuflich und in der Szene Standard, die Datenlage besteht aber ueberwiegend aus kleinen, methodisch schwachen Studien. Metformin ist gut belegt, gilt hier aber als oldschool. | Z52: unter 0,80 (eGFR ueber 110) | AA52: =IF(N(F52)=0,0,F52-ROW()/1000000) | AB52: =SUMPRODUCT(($D$40:$D$81=$D52)*($AA$40:$AA$81>AA52))+1 | AC52: =IF(AA52<=0,0,IF(AB52=1,AA52,0))
A53: Omega-3 hochdosiert | D53: Omega-3 | E53: A | F53: =IF(OR($B53="x",$C53="x"),"",MAX(0,Parameter!$B$36/(((SUM(G328:V328)+SUM(G344:V344))^(1/Parameter!$B$40))*Parameter!$D$88)^(1/Parameter!$B$38)-Parameter!$D$92)) | L53: =Parameter!I268 | N53: =Parameter!K268 | P53: =Parameter!G268 | W53: Triglyzeride unter 1,2 mmol/l. | X53: BESONDERHEIT: reines EPA (Icosapent Ethyl) hebt das LDL nicht an und ist das einzige Omega-3-Praeparat mit positiver Endpunktstudie. KOPPLUNG: der Gefaessnutzen aus REDUCE-IT liess sich nur zum Teil ueber die Triglyzeridsenkung erklaeren, deshalb bleibt er weitgehend entkoppelt. | Z53: 0,80 bis 1,00 (eGFR 85-110) | AA53: =IF(N(F53)=0,0,F53-ROW()/1000000) | AB53: =SUMPRODUCT(($D$40:$D$81=$D53)*($AA$40:$AA$81>AA53))+1 | AC53: =IF(AA53<=0,0,IF(AB53=1,AA53,0))
A54: OTC-Stack komplett | D54: OTC-Stack | E54: B/C | F54: =IF(OR($B54="x",$C54="x"),"",MAX(0,Parameter!$B$36/(((SUM(G328:V328)+SUM(G345:V345))^(1/Parameter!$B$40))*Parameter!$D$88)^(1/Parameter!$B$38)-Parameter!$D$92)) | H54: =Parameter!F269 | I54: =Parameter!E269 | J54: =Parameter!D269 | N54: =Parameter!K269 | P54: =Parameter!G269 | S54: =Parameter!R269 | T54: =Parameter!T269 | W54: LDL unter 2,5 und Triglyzeride unter 1,2 mmol/l. Schafft der Stack das nicht, ist es ein Fall fuer ein Statin - nicht fuer die naechste Dose. | X54: ENTHAELT: Citrus-Bergamotte und Monacolin K auf LDL und HDL, hochdosiertes Omega-3 auf die Triglyzeride, Berberin auf die Glukose, L-Citrullin, Nitrat, Kalium und Taurin auf den Blutdruck, TUDCA und NAC auf die Leber. WER DIE EINZELPOSTEN SCHON ANGEHAKT HAT, HAKT DEN STACK NICHT ZUSAETZLICH AN. Monacolin K IST Lovastatin: nie zusaetzlich zu einem Statin, in der EU seit 2022 unter 3 mg begrenzt, Verbot 2026 auf dem Weg. | Z54: 1,00 bis 1,30 (eGFR 60-85) | AA54: =IF(N(F54)=0,0,F54-ROW()/1000000) | AB54: =SUMPRODUCT(($D$40:$D$81=$D54)*($AA$40:$AA$81>AA54))+1 | AC54: =IF(AA54<=0,0,IF(AB54=1,AA54,0))
A55: Leber-Supplemente (TUDCA, NAC) | D55: Leber-Supplement | E55: C | F55: =IF(OR($B55="x",$C55="x"),"",MAX(0,Parameter!$B$36/(((SUM(G328:V328)+SUM(G346:V346))^(1/Parameter!$B$40))*Parameter!$D$88)^(1/Parameter!$B$38)-Parameter!$D$92)) | S55: =Parameter!R270 | W55: ALT und AST im Normbereich. Bei Kraftsport sind leichte Erhoehungen auch ohne Leberproblem ueblich. | X55: WICHTIG: diese Zeile senkt den Oral-Abzug NICHT. Es gibt keine belastbaren Humandaten, dass TUDCA oder NAC den Schaden 17-alpha-alkylierter Substanzen verhindern. Entkoppelt, weil es fuer die Leber keinen Eingabewert im Blatt gibt. | Z55: ueber 1,30 (eGFR unter 60) | AA55: =IF(N(F55)=0,0,F55-ROW()/1000000) | AB55: =SUMPRODUCT(($D$40:$D$81=$D55)*($AA$40:$AA$81>AA55))+1 | AC55: =IF(AA55<=0,0,IF(AB55=1,AA55,0))
A56: Ausdauertraining und Koerperfett runter | D56: Lifestyle | E56: A | F56: =IF(OR($B56="x",$C56="x"),"",MAX(0,Parameter!$B$36/(((SUM(G328:V328)+SUM(G347:V347))^(1/Parameter!$B$40))*Parameter!$D$88)^(1/Parameter!$B$38)-Parameter!$D$92)) | H56: =Parameter!F271 | J56: =Parameter!D271 | K56: =Parameter!M271 | L56: =Parameter!I271 | N56: =Parameter!K271 | O56: =Parameter!J271 | P56: =Parameter!G271 | S56: =Parameter!R271 | T56: =Parameter!T271 | W56: HDL ueber 1,0 mmol/l, Triglyzeride unter 1,2, Blutdruck unter 130/80. | X56: Das Mittel mit der besten Datenlage auf diesem Blatt, und das einzige mit einem grossen Psyche-Plus. Wirkt bei Depression in der Groessenordnung einer medikamentoesen Behandlung und kostet nichts ausser Zeit. | AA56: =IF(N(F56)=0,0,F56-ROW()/1000000) | AB56: =SUMPRODUCT(($D$40:$D$81=$D56)*($AA$40:$AA$81>AA56))+1 | AC56: =IF(AA56<=0,0,IF(AB56=1,AA56,0))
A57: Salzreduktion | D57: Ernaehrung | E57: A | F57: =IF(OR($B57="x",$C57="x"),"",MAX(0,Parameter!$B$36/(((SUM(G328:V328)+SUM(G348:V348))^(1/Parameter!$B$40))*Parameter!$D$88)^(1/Parameter!$B$38)-Parameter!$D$92)) | J57: =Parameter!D272 | O57: =Parameter!J272 | W57: Blutdruck unter 130/80. | X57: Kostet nichts und wirkt zuverlaessig, besonders bei den salzsensitiven Genotypen dieser Kategorie. | AA57: =IF(N(F57)=0,0,F57-ROW()/1000000) | AB57: =SUMPRODUCT(($D$40:$D$81=$D57)*($AA$40:$AA$81>AA57))+1 | AC57: =IF(AA57<=0,0,IF(AB57=1,AA57,0))
A58: Aromatasehemmer | D58: Aromatasehemmer | E58: B | F58: =IF(OR($B58="x",$C58="x"),"",MAX(0,Parameter!$B$36/(((SUM(G328:V328)+SUM(G349:V349))^(1/Parameter!$B$40))*Parameter!$D$88)^(1/Parameter!$B$38)-Parameter!$D$92)) | H58: =Parameter!F273 | N58: =Parameter!K273 | V58: =Parameter!B273 | W58: E2 im Zielbereich, NICHT gecrasht. HDL dabei mitlaufen lassen. | X58: Ein zu tief gedruecktes E2 kostet Stimmung, Antrieb, Gelenke, Knochendichte und HDL. Deshalb steht hier ein Psyche-Minus, obwohl der Stoff auf dem Papier ein Schutzmittel ist. Niedrigste wirksame Dosis, und nur mit Messwert. | AA58: =IF(N(F58)=0,0,F58-ROW()/1000000) | AB58: =SUMPRODUCT(($D$40:$D$81=$D58)*($AA$40:$AA$81>AA58))+1 | AC58: =IF(AA58<=0,0,IF(AB58=1,AA58,0))
A59: 5-alpha-Reduktase-Hemmer | D59: 5AR-Hemmer | E59: A | F59: =IF(OR($B59="x",$C59="x"),"",MAX(0,Parameter!$B$36/(((SUM(G328:V328)+SUM(G350:V350))^(1/Parameter!$B$40))*Parameter!$D$88)^(1/Parameter!$B$38)-Parameter!$D$92)) | K59: =Parameter!M274 | N59: =Parameter!K274 | W59: Kein Laborziel - der Effekt zeigt sich am Haaransatz, nicht im Blut. | X59: ZWEISCHNEIDIG. Weniger DHT heisst weniger androgener Druck auf den Herzmuskel - deshalb steht dort ein Plus. Dem gegenueber steht das groesste Psyche-Minus dieser Liste: anhaltende Depression, Anhedonie und Libidoverlust nach dem Absetzen sind gut dokumentiert, und es gibt ein Suizidalitaets-Signal. Wer dazu neigt oder eine Vorgeschichte hat, bespricht das vorher mit einem Arzt und nicht mit dem Coach. | AA59: =IF(N(F59)=0,0,F59-ROW()/1000000) | AB59: =SUMPRODUCT(($D$40:$D$81=$D59)*($AA$40:$AA$81>AA59))+1 | AC59: =IF(AA59<=0,0,IF(AB59=1,AA59,0))
A60: ASS niedrig dosiert | D60: Thrombozytenhemmer | E60: A | F60: =IF(OR($B60="x",$C60="x"),"",MAX(0,Parameter!$B$36/(((SUM(G328:V328)+SUM(G351:V351))^(1/Parameter!$B$40))*Parameter!$D$88)^(1/Parameter!$B$38)-Parameter!$D$92)) | L60: =Parameter!I275 | M60: =Parameter!N275 | W60: Kein Laborziel. | X60: Wirkt auf Blutplaettchen, also auf die arterielle Seite. Gegen die venoesen Gerinnungsvarianten dieser Kategorie richtet es fast nichts aus. | AA60: =IF(N(F60)=0,0,F60-ROW()/1000000) | AB60: =SUMPRODUCT(($D$40:$D$81=$D60)*($AA$40:$AA$81>AA60))+1 | AC60: =IF(AA60<=0,0,IF(AB60=1,AA60,0))
A61: Cabergolin oder P5P | D61: Prolaktin | E61: B | F61: =IF(OR($B61="x",$C61="x"),"",MAX(0,Parameter!$B$36/(((SUM(G328:V328)+SUM(G352:V352))^(1/Parameter!$B$40))*Parameter!$D$88)^(1/Parameter!$B$38)-Parameter!$D$92)) | N61: =Parameter!K276 | W61: Prolaktin im Normbereich. | X61: Holt Stimmung und Libido zurueck, wenn ein hohes Prolaktin der Grund war. Cabergolin selbst kann dafuer Impulskontrolle und Schlaf stoeren - niedrig dosieren, und nur mit gemessenem Prolaktin. | AA61: =IF(N(F61)=0,0,F61-ROW()/1000000) | AB61: =SUMPRODUCT(($D$40:$D$81=$D61)*($AA$40:$AA$81>AA61))+1 | AC61: =IF(AA61<=0,0,IF(AB61=1,AA61,0))
A62: SERM (Tamoxifen, Raloxifen, Enclomifen) | D62: SERM | E62: B | F62: =IF(OR($B62="x",$C62="x"),"",MAX(0,Parameter!$B$36/(((SUM(G328:V328)+SUM(G353:V353))^(1/Parameter!$B$40))*Parameter!$D$88)^(1/Parameter!$B$38)-Parameter!$D$92)) | N62: =Parameter!K277 | V62: =Parameter!B277 | W62: Bruestgewebe ruhig, E2 im Zielbereich - NICHT gecrasht. | X62: Halbes Gesundheitsplus wie der Aromatasehemmer, dafuer Minus beim Muskelaufbau - und ein Psyche-Minus: Stimmungstief, Reizbarkeit und Sehstoerungen sind bei Clomifen haeufig, bei Tamoxifen seltener. | AA62: =IF(N(F62)=0,0,F62-ROW()/1000000) | AB62: =SUMPRODUCT(($D$40:$D$81=$D62)*($AA$40:$AA$81>AA62))+1 | AC62: =IF(AA62<=0,0,IF(AB62=1,AA62,0))
A63: Testosteron | D63: Basis | E63: A | W63: Haematokrit unter 47, HDL ueber 1,0, Blutdruck unter 130/80. | X63: DIE GRUNDLAST. Sie steckt bereits im Gesamt-Load oben und bekommt deshalb hier keine eigenen Faktoren - sonst waere sie doppelt gezaehlt. Alle folgenden Zeilen zeigen, was eine Substanz ZUSAETZLICH zu Testosteron auf einzelne Systeme legt. Testosteron aromatisiert, und das ist fuer die Blutfette ein Vorteil: in Studien verschlechterte gerade das BLOCKIEREN der Aromatase das Lipidprofil.
A64: Nandrolon | D64: 19-Nor | E64: B | G64: =Parameter!O279 | H64: =Parameter!F279 | J64: =Parameter!D279 | K64: =Parameter!M279 | N64: =Parameter!K279 | O64: =Parameter!J279 | W64: Prolaktin im Normbereich, HDL ueber 1,0. | X64: 19-Nor. PROLAKTIN ist der Punkt, den die Liste noch nicht als Kategorie hat - Cabergolin oder P5P gehoeren hier ins Blickfeld, ebenso die progestogene Wirkung. Auf die Blutfette vergleichsweise moderat (rund 25 Prozent HDL-Abfall in einer Crossover-Studie), am Herzmuskel dagegen der auffaelligste der Injizierbaren.
A65: Trenbolon | D65: 19-Nor | E65: B | G65: =Parameter!O280 | H65: =Parameter!F280 | J65: =Parameter!D280 | K65: =Parameter!M280 | N65: =Parameter!K280 | O65: =Parameter!J280 | Q65: =Parameter!L280 | R65: =Parameter!Q280 | V65: =Parameter!B280 | W65: Kein Zielwert macht das gut. Wenn ueberhaupt: Cystatin C unter 0,90, HDL ueber 1,0, Blutdruck unter 130/80, Prolaktin normal. | X65: Der Stoff mit dem breitesten Schadensprofil auf diesem Blatt. 19-Nor, aromatisiert nicht (deshalb der E2-Eintrag: fehlendes Estrogen ist fuer Blutfette und Gelenke ein Nachteil, nicht nur fuer die Libido), starke Prolaktin- und Progesteronwirkung, in Fallberichten und Tiermodellen Hinweise auf Nierenschaedigung und Kardiomyopathie. Dazu Schlafstoerungen und Blutdruck. Wer den Score sehen will, ohne ihn zu veraendern, hakt genau diese Zeile an und aus.
A66: Boldenon | D66: Sonstige AAS | E66: C | G66: =Parameter!O281 | H66: =Parameter!F281 | N66: =Parameter!K281 | O66: =Parameter!J281 | R66: =Parameter!Q281 | W66: Haematokrit unter 47 - hier der entscheidende Wert. | X66: Treibt die Erythropoese staerker als die meisten anderen. Wer Boldenon faehrt, kontrolliert den Haematokrit engmaschig und plant die Blutspende von vornherein ein. Auf die Blutfette vergleichsweise freundlich.
A67: Primobolan (Methenolon) | D67: DHT-Derivat | E67: C | G67: =Parameter!O283 | H67: =Parameter!F283 | V67: =Parameter!B283 | W67: HDL ueber 1,0. | X67: Der mildeste der gaengigen Injizierbaren - aber nicht neutral am Oestrogen: Methenolon draengt E2 staerker nach unten als Drostanolon. Zu tiefes E2 ist kein Gewinn, sondern kostet Gelenke, Knochendichte, Libido und HDL, deshalb steht hier ein Minus und kein Plus. Ansonsten weniger auffaellig als der Rest der Klasse, was ihn nicht harmlos macht.
A68: Drostanolon | D68: DHT-Derivat | E68: C | G68: =Parameter!O282 | H68: =Parameter!F282 | V68: =Parameter!B282 | W68: HDL ueber 1,0. | X68: DHT-Derivat, aromatisiert nicht. Typisches Muster der Klasse: HDL runter, Haare und Prostata belastet, Estradiol gedrueckt. Der E2-Eintrag ist kein Tippfehler - zu wenig Estrogen ist ebenfalls ein Problem.
A69: Turinabol | D69: Oral 17-aa | E69: C | G69: =Parameter!O288 | H69: =Parameter!F288 | I69: =Parameter!E288 | N69: =Parameter!K288 | O69: =Parameter!J288 | S69: =Parameter!R288 | W69: HDL ueber 1,0, ALT und AST im Rahmen. | X69: ORAL, 17-alpha-alkyliert: zusaetzlich oben den Oral-Schalter setzen. Milder als die uebrigen Orale, aromatisiert nicht.
A70: Oxandrolon | D70: Oral 17-aa | E70: B | G70: =Parameter!O284 | H70: =Parameter!F284 | I70: =Parameter!E284 | N70: =Parameter!K284 | O70: =Parameter!J284 | R70: =Parameter!Q284 | S70: =Parameter!R284 | W70: HDL ueber 1,0, ALT und AST im Rahmen. | X70: Der leberfreundlichste der 17-alpha-alkylierten - deshalb hier weniger Leberminus als bei den anderen. Dafuer ein eigenes Nierenthema: Kreatininanstieg und Belastung der Niere sind gut dokumentiert und werden gern als 'nur mehr Muskelmasse' wegerklaert. Das Lipidprofil bleibt uebel.
A71: Methandienon | D71: Oral 17-aa | E71: B | G71: =Parameter!O287 | H71: =Parameter!F287 | I71: =Parameter!E287 | J71: =Parameter!D287 | N71: =Parameter!K287 | O71: =Parameter!J287 | S71: =Parameter!R287 | V71: =Parameter!B287 | W71: ALT und AST im Rahmen, Blutdruck unter 130/80, E2 im Zielbereich. | X71: ORAL, 17-alpha-alkyliert: zusaetzlich oben den Oral-Schalter setzen. Aromatisiert stark, daher der E2-Eintrag und die Wassereinlagerung, die den Blutdruck treibt.
A72: Stanozolol | D72: Oral 17-aa | E72: B | G72: =Parameter!O285 | H72: =Parameter!F285 | I72: =Parameter!E285 | L72: =Parameter!I285 | N72: =Parameter!K285 | O72: =Parameter!J285 | S72: =Parameter!R285 | W72: HDL ueber 1,0, LDL unter 2,5, ALT und AST im Rahmen. | X72: Der Stoff mit dem deutlichsten Kollagenproblem: verminderte Elastizitaet von Sehnen bis zur Gefaesswand, deshalb hier das groesste Minus der Liste. Dazu das schlechteste Lipidprofil aller gaengigen Oralen.
A73: Oxymetholon | D73: Oral 17-aa | E73: B | G73: =Parameter!O286 | H73: =Parameter!F286 | I73: =Parameter!E286 | J73: =Parameter!D286 | N73: =Parameter!K286 | O73: =Parameter!J286 | S73: =Parameter!R286 | W73: ALT und AST im Rahmen, Haematokrit unter 47, Blutdruck unter 130/80. | X73: ORAL, 17-alpha-alkyliert: zusaetzlich oben den Oral-Schalter setzen. Auf die Leber und den Haematokrit der haerteste der gaengigen Orale, dazu Wassereinlagerung und Blutdruck.
A74: SARM (RAD-140, LGD-4033, Ostarin) | D74: SARM | E74: C | G74: =Parameter!O289 | H74: =Parameter!F289 | I74: =Parameter!E289 | N74: =Parameter!K289 | S74: =Parameter!R289 | W74: HDL ueber 1,0, ALT und AST im Rahmen. | X74: Werden als milde Alternative verkauft und sind es nicht. Zu mehreren Vertretern gibt es Fallberichte ueber schwere Leberschaeden, das HDL faellt aehnlich deutlich wie unter Oralen. Keiner davon ist als Arzneimittel zugelassen, die Produktqualitaet auf dem grauen Markt ist entsprechend unklar.
A75: Wachstumshormon (hGH) | D75: Peptidhormon | E75: B | J75: =Parameter!D290 | K75: =Parameter!M290 | O75: =Parameter!J290 | T75: =Parameter!T290 | W75: Nuechternglukose unter 93 mg/dl bzw. HbA1c unter 5,7. | X75: Was bei Akromegalie zu sehen ist - erweiterte Aortenwurzel und undichte Aortenklappe - ist der Grund fuer das Minus an der Gefaesswand. Bei den hier ueblichen Dosen abgeschwaecht, aber in dieselbe Richtung.
A76: Insulin | D76: Insulin | E76: A | T76: =Parameter!T291 | W76: Nuechternglukose unter 93 mg/dl. | X76: Das eigentliche Risiko bildet dieser Score NICHT ab: eine Unterzuckerung kann innerhalb von Stunden toedlich sein, unabhaengig von jedem Punktwert hier. Der Eintrag steht fuer die laengerfristige Stoffwechselwirkung.
A77: Clenbuterol | D77: Beta-2-Agonist | E77: C | G77: =Parameter!O292 | I77: =Parameter!E292 | K77: =Parameter!M292 | N77: =Parameter!K292 | O77: =Parameter!J292 | P77: =Parameter!G292 | Q77: =Parameter!L292 | T77: =Parameter!T292 | W77: Ruhepuls und Rhythmus unauffaellig. | X77: Zwei Gesichter. Als Beta-2-Agonist verbrennt er Fett und verbessert dabei Blutzucker und Triglyzeride - das sind die Pluszeichen. Dem gegenueber stehen Herzrhythmus, Herzmuskel und Psyche: Tremor, Herzrasen, Schlaflosigkeit und Panik. Baut ausser Fett auch Muskel ab.
A78: T3 (Liothyronin) | D78: Schilddruesenhormon | E78: B | K78: =Parameter!M293 | N78: =Parameter!K293 | Q78: =Parameter!L293 | W78: TSH, fT3 und fT4 im Normbereich, Ruhepuls unauffaellig. | X78: Baut nicht nur Fett ab, sondern auch Muskel - daher der Minuseintrag beim Muskelaufbau. Am Herzen Rhythmusstoerungen und bei Dauergebrauch Hypertrophie. Nach dem Absetzen braucht die eigene Achse Zeit.
A79: DNP | D79: Entkoppler | E79: A | N79: =Parameter!K294 | Q79: =Parameter!L294 | R79: =Parameter!Q294 | S79: =Parameter!R294 | W79: Es gibt hier keinen Zielwert, der das sicher macht. | X79: KEIN PUNKTWERT AUF DIESEM BLATT BILDET DAS RICHTIG AB. DNP entkoppelt die Zellatmung; die toedliche Dosis liegt nah an der wirksamen, und es gibt keinen Gegenspieler. Todesfaelle sind aus normalen Anwendungsdosen dokumentiert, nicht nur aus Ueberdosierungen. Die Zeile steht hier, damit der Score nicht so tut, als waere die Substanz kostenlos - nicht, weil sich das Risiko in Punkten ausdruecken liesse.
A80: Rauchen (10 Zigaretten pro Tag) | D80: Rauchen | E80: A | G80: =Parameter!O295 | H80: =Parameter!F295 | I80: =Parameter!E295 | J80: =Parameter!D295 | K80: =Parameter!M295 | L80: =Parameter!I295 | M80: =Parameter!N295 | N80: =Parameter!K295 | O80: =Parameter!J295 | Q80: =Parameter!L295 | R80: =Parameter!Q295 | T80: =Parameter!T295 | W80: Null. Es gibt keine unbedenkliche Menge. | X80: Der groesste Einzelwert dieser Liste steht bei der Gefaesswand, und das ist kein Versehen: aktuelle Raucher haben ein rund fuenffaches Risiko fuer ein Bauchaortenaneurysma, je zehn Zigaretten taeglich kommt ein Faktor 1,9 dazu. In dieser Kategorie steckt seit dieser Fassung auch die Lunge - Emphysem und Aneurysma sind dieselbe Biologie, zerlegtes Elastin. HERZ UND SCHLAGANFALL SKALIEREN NICHT LINEAR: schon eine Zigarette am Tag traegt rund 46 Prozent des Ueberrisikos von zwanzig. Zehn am Tag sind naeher an einer Schachtel als an der Haelfte, Runterrauchen bringt also weit weniger als es sich anfuehlt. Dazu die Raucherpolyglobulie: Kohlenmonoxid bindet Haemoglobin, der Koerper legt Erythrozyten nach - auf einem System, das der Stack ohnehin hochtreibt. NICHT ABGEBILDET: Krebs. Das Modell kennt keine Krebskategorie, deshalb ist der Wert hier eher zu freundlich als zu hart.
A81: Alkohol (5 Bier pro Tag) | D81: Alkohol | E81: A | J81: =Parameter!D296 | K81: =Parameter!M296 | L81: =Parameter!I296 | N81: =Parameter!K296 | O81: =Parameter!J296 | P81: =Parameter!G296 | Q81: =Parameter!L296 | S81: =Parameter!R296 | T81: =Parameter!T296 | W81: Unter 100 g Reinalkohol pro Woche, das sind rund vier bis fuenf Bier die WOCHE. Fuenf am Tag sind das Sieben- bis Zehnfache davon. | X81: Fuenf Bier taeglich sind rund 100 g Reinalkohol am Tag und damit etwa 700 g die Woche. Ab 350 g die Woche kostet Alkohol rund vier bis fuenf Jahre Lebenserwartung ab 40 - das ist die Groessenordnung, in der hier gerechnet wird, und die Menge liegt beim Doppelten dieser Schwelle. Blutdruck steigt dosisabhaengig um grob 1 mmHg je 10 g am Tag, Triglyzeride reagieren stark, Vorhofflimmern und die alkoholische Kardiomyopathie kommen bei dieser Dauerlast dazu, und die Leber ist das Organ, das zuerst nachgibt. KEIN HDL-PLUS: Alkohol hebt das HDL messbar, aber Mendelsche Randomisierung zeigt, dass dieses HDL nicht schuetzt. Ein Pluszeichen dafuer waere geschoent. NICHT ABGEBILDET: Krebs - Alkohol ist als Gruppe-1-Karzinogen eingestuft, das Modell hat dafuer keine Kategorie.
A83: Rechenhilfe - nicht anfassen
A84: W (max Malus) | G84: 8.3333 | H84: 8.3333 | I84: 8.3333 | J84: 8.3333 | K84: 8.3333 | L84: 8.3333 | M84: 8.3333 | N84: 8.3333 | O84: 8.3333 | P84: 4.1667 | Q84: 4.1667 | R84: 4.1667 | S84: 4.1667 | T84: 4.1667 | U84: 2.0833 | V84: 2.0833
A85: Index genetisch | G85: 0.2 | H85: 0.2 | I85: 0.2 | J85: 0.2 | K85: 0.2 | L85: 0.2 | M85: 0.2 | N85: 0.2 | O85: 0.2 | P85: 0.2 | Q85: 0.2 | R85: 0.2 | S85: 0.2 | T85: 0.2 | U85: 0.2 | V85: 0.2
A86: Load-Empfindlichkeit | G86: =Parameter!$B$70 | H86: =Parameter!$B$66 | I86: =Parameter!$B$67 | J86: =Parameter!$B$65 | K86: =Parameter!$B$71 | L86: =Parameter!$B$76 | M86: =Parameter!$B$74 | N86: =Parameter!$B$73 | O86: =Parameter!$B$77 | P86: =Parameter!$B$68 | Q86: =Parameter!$B$78 | R86: =Parameter!$B$79 | S86: =Parameter!$B$72 | T86: =Parameter!$B$69 | U86: =Parameter!$B$80 | V86: =Parameter!$B$75
A87: Anwendungsdauer in Jahren | G87: =IF($C$8="<5 Jahre",Parameter!$B$21,IF($C$8="10 Jahre",Parameter!$B$22,IF($C$8="15 Jahre",Parameter!$B$23,999)))
A88: Load-Faktor effektiv | G88: =1+(IF($C$6="Natty oder TRT (400-1000 ng/dl)",Parameter!$B$8,IF($C$6="TRT plus (1000-1400 ng/dl)",Parameter!$B$9,IF($C$6="Blast moderat (250-350 mg/Woche)",Parameter!$B$10,IF($C$6="Blast fortgeschritten (500-750 mg/Woche)",Parameter!$B$11,IF($C$6="Blast Profi (1 g und mehr)",Parameter!$B$12,1.0)))))-1)*IF($C$7="Dauerblast (durchgehend)",Parameter!$B$16,IF($C$7="Blast and Cruise (Time On = Time Off)",Parameter!$B$17,1.0))
A89: rechnerisches Endalter | G89: =Parameter!$D$126
A90: Endalter nach Massnahmen | G90: =Parameter!$D$127
A91: gemessen (1/0) | G91: =IF(OR($C$15="",$C$15="nicht gemessen"),0,1) | H91: =IF(OR($C$17="",$C$17="nicht gemessen"),0,1) | I91: =IF(OR($C$16="",$C$16="nicht gemessen"),0,1) | J91: =IF(OR($C$14="",$C$14="nicht gemessen"),0,1) | K91: 0 | L91: 0 | M91: 0 | N91: 0 | O91: 0 | P91: =IF(OR($C$18="",$C$18="nicht gemessen"),0,1) | Q91: 0 | R91: =IF(OR($C$20="",$C$20="nicht gemessen"),0,1) | S91: 0 | T91: =IF(OR($C$19="",$C$19="nicht gemessen"),0,1) | U91: 0 | V91: 0
A92: Index Messung | G92: =IF($C$15="unter 45",Parameter!$B$44,IF($C$15="45 bis 50",Parameter!$B$45,IF($C$15="50 bis 54",Parameter!$B$46,Parameter!$B$47))) | H92: =IF($C$17="ueber 1,3 (50 mg/dl)",Parameter!$B$44,IF($C$17="1,0 bis 1,3 (39-50 mg/dl)",Parameter!$B$45,IF($C$17="0,6 bis 1,0 (23-39 mg/dl)",Parameter!$B$46,Parameter!$B$47))) | I92: =IF($C$16="unter 1,4 (55 mg/dl)",Parameter!$B$44,IF($C$16="1,4 bis 2,6 (55-100 mg/dl)",Parameter!$B$45,IF($C$16="2,6 bis 3,4 (100-130 mg/dl)",Parameter!$B$46,Parameter!$B$47))) | J92: =IF($C$14="unter 115",Parameter!$B$44,IF($C$14="115 bis 125",Parameter!$B$45,IF($C$14="125 bis 140",Parameter!$B$46,Parameter!$B$47))) | K92: 0 | L92: 0 | M92: 0 | N92: 0 | O92: 0 | P92: =IF($C$18="unter 1,0 (89 mg/dl)",Parameter!$B$44,IF($C$18="1,0 bis 1,7 (89-150 mg/dl)",Parameter!$B$45,IF($C$18="1,7 bis 3,4 (150-300 mg/dl)",Parameter!$B$46,Parameter!$B$47))) | Q92: 0 | R92: =IF($C$20="unter 0,80 (eGFR ueber 110)",Parameter!$B$44,IF($C$20="0,80 bis 1,00 (eGFR 85-110)",Parameter!$B$45,IF($C$20="1,00 bis 1,30 (eGFR 60-85)",Parameter!$B$46,Parameter!$B$47))) | S92: 0 | T92: =IF($C$19="unter 80 (4,4 mmol/l)",Parameter!$B$44,IF($C$19="80 bis 95 (4,4-5,3 mmol/l)",Parameter!$B$45,IF($C$19="95 bis 110 (5,3-6,1 mmol/l)",Parameter!$B$46,Parameter!$B$47))) | U92: 0 | V92: 0
A93: Endlevel (1/0) | G93: =IF($C$15="ueber 54",1,0) | H93: =IF($C$17="unter 0,6 (unter 23 mg/dl)",1,0) | I93: =IF($C$16="ueber 3,4 (ueber 130 mg/dl)",1,0) | J93: =IF($C$14="ab 140",1,0) | K93: 0 | L93: 0 | M93: 0 | N93: 0 | O93: 0 | P93: =IF($C$18="ueber 3,4 (ueber 300 mg/dl)",1,0) | Q93: 0 | R93: =IF($C$20="ueber 1,30 (eGFR unter 60)",1,0) | S93: 0 | T93: =IF($C$19="ab 110 (ab 6,1 mmol/l)",1,0) | U93: 0 | V93: 0
A94: Stufe je Messwert | G94: =IF(OR($C$14="",$C$14="nicht gemessen"),1,IF($C$14="unter 115",Parameter!$B$51,IF($C$14="115 bis 125",Parameter!$B$52,IF($C$14="125 bis 140",Parameter!$B$53,Parameter!$B$54)))) | H94: =IF(OR($C$15="",$C$15="nicht gemessen"),1,IF($C$15="unter 45",Parameter!$B$51,IF($C$15="45 bis 50",Parameter!$B$52,IF($C$15="50 bis 54",Parameter!$B$53,Parameter!$B$54)))) | I94: =IF(OR($C$16="",$C$16="nicht gemessen"),1,IF($C$16="unter 1,4 (55 mg/dl)",Parameter!$B$51,IF($C$16="1,4 bis 2,6 (55-100 mg/dl)",Parameter!$B$52,IF($C$16="2,6 bis 3,4 (100-130 mg/dl)",Parameter!$B$53,Parameter!$B$54)))) | J94: =IF(OR($C$17="",$C$17="nicht gemessen"),1,IF($C$17="ueber 1,3 (50 mg/dl)",Parameter!$B$51,IF($C$17="1,0 bis 1,3 (39-50 mg/dl)",Parameter!$B$52,IF($C$17="0,6 bis 1,0 (23-39 mg/dl)",Parameter!$B$53,Parameter!$B$54)))) | K94: =IF(OR($C$18="",$C$18="nicht gemessen"),1,IF($C$18="unter 1,0 (89 mg/dl)",Parameter!$B$51,IF($C$18="1,0 bis 1,7 (89-150 mg/dl)",Parameter!$B$52,IF($C$18="1,7 bis 3,4 (150-300 mg/dl)",Parameter!$B$53,Parameter!$B$54)))) | L94: =IF(OR($C$19="",$C$19="nicht gemessen"),1,IF($C$19="unter 80 (4,4 mmol/l)",Parameter!$B$51,IF($C$19="80 bis 95 (4,4-5,3 mmol/l)",Parameter!$B$52,IF($C$19="95 bis 110 (5,3-6,1 mmol/l)",Parameter!$B$53,Parameter!$B$54)))) | M94: =IF(OR($C$20="",$C$20="nicht gemessen"),1,IF($C$20="unter 0,80 (eGFR ueber 110)",Parameter!$B$51,IF($C$20="0,80 bis 1,00 (eGFR 85-110)",Parameter!$B$52,IF($C$20="1,00 bis 1,30 (eGFR 60-85)",Parameter!$B$53,Parameter!$B$54))))
A95: Index real | G95: =MIN(1,IF(G93=1,1,IF(G91=1,1-(1-(Parameter!$B$57*G92+(1-Parameter!$B$57)*G85))^(1+(G$88-1)*G86*Parameter!$B$58),1-(1-G85)^(1+(G$88-1)*G86)))) | H95: =MIN(1,IF(H93=1,1,IF(H91=1,1-(1-(Parameter!$B$57*H92+(1-Parameter!$B$57)*H85))^(1+(G$88-1)*H86*Parameter!$B$58),1-(1-H85)^(1+(G$88-1)*H86)))) | I95: =MIN(1,IF(I93=1,1,IF(I91=1,1-(1-(Parameter!$B$57*I92+(1-Parameter!$B$57)*I85))^(1+(G$88-1)*I86*Parameter!$B$58),1-(1-I85)^(1+(G$88-1)*I86)))) | J95: =MIN(1,IF(J93=1,1,IF(J91=1,1-(1-(Parameter!$B$57*J92+(1-Parameter!$B$57)*J85))^(1+(G$88-1)*J86*Parameter!$B$58),1-(1-J85)^(1+(G$88-1)*J86)))) | K95: =MIN(1,IF(K93=1,1,IF(K91=1,1-(1-(Parameter!$B$57*K92+(1-Parameter!$B$57)*K85))^(1+(G$88-1)*K86*Parameter!$B$58),1-(1-K85)^(1+(G$88-1)*K86)))) | L95: =MIN(1,IF(L93=1,1,IF(L91=1,1-(1-(Parameter!$B$57*L92+(1-Parameter!$B$57)*L85))^(1+(G$88-1)*L86*Parameter!$B$58),1-(1-L85)^(1+(G$88-1)*L86)))) | M95: =MIN(1,IF(M93=1,1,IF(M91=1,1-(1-(Parameter!$B$57*M92+(1-Parameter!$B$57)*M85))^(1+(G$88-1)*M86*Parameter!$B$58),1-(1-M85)^(1+(G$88-1)*M86)))) | N95: =MIN(1,IF(N93=1,1,IF(N91=1,1-(1-(Parameter!$B$57*N92+(1-Parameter!$B$57)*N85))^(1+(G$88-1)*N86*Parameter!$B$58),1-(1-N85)^(1+(G$88-1)*N86)))) | O95: =MIN(1,IF(O93=1,1,IF(O91=1,1-(1-(Parameter!$B$57*O92+(1-Parameter!$B$57)*O85))^(1+(G$88-1)*O86*Parameter!$B$58),1-(1-O85)^(1+(G$88-1)*O86)))) | P95: =MIN(1,IF(P93=1,1,IF(P91=1,1-(1-(Parameter!$B$57*P92+(1-Parameter!$B$57)*P85))^(1+(G$88-1)*P86*Parameter!$B$58),1-(1-P85)^(1+(G$88-1)*P86)))) | Q95: =MIN(1,IF(Q93=1,1,IF(Q91=1,1-(1-(Parameter!$B$57*Q92+(1-Parameter!$B$57)*Q85))^(1+(G$88-1)*Q86*Parameter!$B$58),1-(1-Q85)^(1+(G$88-1)*Q86)))) | R95: =MIN(1,IF(R93=1,1,IF(R91=1,1-(1-(Parameter!$B$57*R92+(1-Parameter!$B$57)*R85))^(1+(G$88-1)*R86*Parameter!$B$58),1-(1-R85)^(1+(G$88-1)*R86)))) | S95: =MIN(1,IF(S93=1,1,IF(S91=1,1-(1-(Parameter!$B$57*S92+(1-Parameter!$B$57)*S85))^(1+(G$88-1)*S86*Parameter!$B$58),1-(1-S85)^(1+(G$88-1)*S86)))) | T95: =MIN(1,IF(T93=1,1,IF(T91=1,1-(1-(Parameter!$B$57*T92+(1-Parameter!$B$57)*T85))^(1+(G$88-1)*T86*Parameter!$B$58),1-(1-T85)^(1+(G$88-1)*T86)))) | U95: =MIN(1,IF(U93=1,1,IF(U91=1,1-(1-(Parameter!$B$57*U92+(1-Parameter!$B$57)*U85))^(1+(G$88-1)*U86*Parameter!$B$58),1-(1-U85)^(1+(G$88-1)*U86)))) | V95: =MIN(1,IF(V93=1,1,IF(V91=1,1-(1-(Parameter!$B$57*V92+(1-Parameter!$B$57)*V85))^(1+(G$88-1)*V86*Parameter!$B$58),1-(1-V85)^(1+(G$88-1)*V86))))
G96: =G84*G95 | H96: =H84*H95 | I96: =I84*I95 | J96: =J84*J95 | K96: =K84*K95 | L96: =L84*L95 | M96: =M84*M95 | N96: =N84*N95 | ... V96: =V84*V95
A97: A) laeuft bereits
A98: · PCSK9-Hemmer oder Inclisiran | G98: =IF(AND($B40="x",G91=0),G40,0) | H98: =IF(AND($B40="x",H91=0),H40,0) | I98: =IF(AND($B40="x",I91=0),I40,0) | J98: =IF(AND($B40="x",J91=0),J40,0) | K98: =IF(AND($B40="x",K91=0),K40,0) | L98: =IF(AND($B40="x",L91=0),L40,0) | M98: =IF(AND($B40="x",M91=0),M40,0) | N98: =IF(AND($B40="x",N91=0),N40,0) | ... V98: =IF(AND($B40="x",V91=0),V40,0)
A99: · Statin | G99: =IF(AND($B41="x",G91=0),G41,0) | H99: =IF(AND($B41="x",H91=0),H41,0) | I99: =IF(AND($B41="x",I91=0),I41,0) | J99: =IF(AND($B41="x",J91=0),J41,0) | K99: =IF(AND($B41="x",K91=0),K41,0) | L99: =IF(AND($B41="x",L91=0),L41,0) | M99: =IF(AND($B41="x",M91=0),M41,0) | N99: =IF(AND($B41="x",N91=0),N41,0) | ... S99: =IF(AND($B41="x",S91=0),S41,0) | T99: =IF(OR($B41="x",$C41="x"),T41,0) | U99: =IF(AND($B41="x",U91=0),U41,0) | V99: =IF(AND($B41="x",V91=0),V41,0)
A100: · Ezetimib | G100: =IF(AND($B42="x",G91=0),G42,0) | H100: =IF(AND($B42="x",H91=0),H42,0) | I100: =IF(AND($B42="x",I91=0),I42,0) | J100: =IF(AND($B42="x",J91=0),J42,0) | K100: =IF(AND($B42="x",K91=0),K42,0) | L100: =IF(AND($B42="x",L91=0),L42,0) | M100: =IF(AND($B42="x",M91=0),M42,0) | N100: =IF(AND($B42="x",N91=0),N42,0) | ... V100: =IF(AND($B42="x",V91=0),V42,0)
A101: · Bempedoinsaeure | G101: =IF(AND($B43="x",G91=0),G43,0) | H101: =IF(AND($B43="x",H91=0),H43,0) | I101: =IF(AND($B43="x",I91=0),I43,0) | J101: =IF(AND($B43="x",J91=0),J43,0) | K101: =IF(AND($B43="x",K91=0),K43,0) | L101: =IF(AND($B43="x",L91=0),L43,0) | M101: =IF(AND($B43="x",M91=0),M43,0) | N101: =IF(AND($B43="x",N91=0),N43,0) | ... V101: =IF(AND($B43="x",V91=0),V43,0)
A102: · Sartan (ARB) | G102: =IF(AND($B44="x",G91=0),G44,0) | H102: =IF(AND($B44="x",H91=0),H44,0) | I102: =IF(AND($B44="x",I91=0),I44,0) | J102: =IF(AND($B44="x",J91=0),J44,0) | K102: =IF(AND($B44="x",K91=0),K44,0) | L102: =IF(AND($B44="x",L91=0),L44,0) | M102: =IF(AND($B44="x",M91=0),M44,0) | N102: =IF(AND($B44="x",N91=0),N44,0) | ... V102: =IF(AND($B44="x",V91=0),V44,0)
A103: · ACE-Hemmer | G103: =IF(AND($B45="x",G91=0),G45,0) | H103: =IF(AND($B45="x",H91=0),H45,0) | I103: =IF(AND($B45="x",I91=0),I45,0) | J103: =IF(AND($B45="x",J91=0),J45,0) | K103: =IF(AND($B45="x",K91=0),K45,0) | L103: =IF(AND($B45="x",L91=0),L45,0) | M103: =IF(AND($B45="x",M91=0),M45,0) | N103: =IF(AND($B45="x",N91=0),N45,0) | ... V103: =IF(AND($B45="x",V91=0),V45,0)
...

Sheet Parameter
A1: Parameter - hier laesst sich alles nachjustieren
A2: Spalte B ist die Stellschraube, Spalte C nennt den Wert, mit dem ausgeliefert wurde. Wer sich verstellt hat, traegt einfach den Default wieder ein. Der Stack-Planer rechnet direkt mit Spalte B - jede Aenderung wirkt sofort. Was NICHT hier steht: die Wirkfaktoren der Substanzen (Block Matrix weiter unten) und ihre Kopplung (Block Kopplung weiter unten).
A3: Die Werte sind gesetzt, nicht gemessen. Sie beruhen auf durchschnittlichen Effektstaerken aus Studien und auf Einschaetzung, wo es keine Studien gibt. Wer sie fuer zu milde oder zu hart haelt, hat moeglicherweise recht - deshalb stehen sie hier und nicht im Programmcode.
A5: 1. Gesamt-Load
A6: Multiplikator auf den Belastungsindex. Er wirkt auf den UEBERSCHUSS ueber 1, nicht auf den ganzen Wert: effektiv = 1 + (Load - 1) * Art * Dauer * Alter. Deshalb bleibt Natty/TRT immer bei 1,00 - das ist die Grundlinie, gegen die alles andere gerechnet wird.
A7: Stufe oder Groesse | B7: Wert | C7: Default | D7: Bedeutung
A8: Natty oder TRT (400-1000 ng/dl) | B8: 1 | C8: 1 | D8: Grundlinie, hier passiert nichts.
A9: TRT plus (1000-1400 ng/dl) | B9: 2.1 | C9: 2.1 | D9: Belastung dieser Stufe gegenueber der Grundlinie.
A10: Blast moderat (250-350 mg/Woche) | B10: 3 | C10: 3 | D10: Belastung dieser Stufe gegenueber der Grundlinie.
A11: Blast fortgeschritten (500-750 mg/Woche) | B11: 5 | C11: 5 | D11: Belastung dieser Stufe gegenueber der Grundlinie.
A12: Blast Profi (1 g und mehr) | B12: 8 | C12: 8 | D12: Belastung dieser Stufe gegenueber der Grundlinie.
A13: 2. Anwendungsart
A14: Daempft oder verstaerkt den Load-Ueberschuss. Ab Natty/TRT ohne Wirkung, weil es dort keinen Ueberschuss gibt.
A15: Stufe oder Groesse | B15: Wert | C15: Default | D15: Bedeutung
A16: Dauerblast (durchgehend) | B16: 1 | C16: 1 | D16: Durchgehend, kein Erholungsfenster.
A17: Blast and Cruise (Time On = Time Off) | B17: 0.6 | C17: 0.6 | D17: Nur wenn die Pause so lang ist wie der Block, mit echtem TRT dazwischen.
A18: 3. Geplante Anwendungsdauer
A19: Nur noch die Anzahl Jahre - kein eigener Daempfungsfaktor mehr. Die Dauer wirkt ueber die Jahres-Tabelle auf dem Block Lebensuhr weiter unten: jedes Jahr unter Last kostet einzeln, und zwar mit dem Jahresfaktor des Alters, in dem man es verbringt. Deshalb ist ein Jahr mit 55 teurer als eines mit 25, ohne dass irgendwo eine Altersstufe eingestellt werden muesste.
A20: Stufe oder Groesse | B20: Wert | C20: Default | D20: Bedeutung
A21: <5 Jahre | B21: 5 | C21: 5 | D21: So viele Jahre laeuft die Last.
A22: 10 Jahre | B22: 10 | C22: 10 | D22: So viele Jahre laeuft die Last.
A23: 15 Jahre | B23: 15 | C23: 15 | D23: So viele Jahre laeuft die Last.
A24: bis dass der Tod uns scheidet | B24: - | C24: - | D24: Keine Zahl. Die Uhr laeuft weiter, bis das Budget leer ist - das Endalter faellt von selbst heraus.
A25: 4. Jahresfaktor: was ein Lebensjahr kostet
A26: f(Alter) = (1 + LINEAR * (Alter - Basisalter)) * ZINS ^ (Alter - Basisalter). Der lineare Teil gibt den gleichmaessigen Zuwachs, der Zinseszinsteil sorgt dafuer, dass die Kurve mit den Jahren von selbst steiler wird. Mit den Defaults: 20 = 1,00 - 21 = 1,01 - 30 = 1,10 - 40 = 1,22 - 60 = 1,47 - 88 = 1,88. LINEAR auf 0 macht die Kurve rein exponentiell, ZINS auf 1,000 macht sie rein linear. Die ganze Tabelle steht sichtbar auf dem Block Lebensuhr weiter unten.
A27: Stufe oder Groesse | B27: Wert | C27: Default | D27: Bedeutung
A28: Basisalter (Faktor genau 1,00) | B28: 20 | C28: 20 | D28: Der Nullpunkt der Kurve. Hier kostet ein Jahr genau eine Einheit.
A29: linearer Zuwachs je Jahr | B29: 0.005 | C29: 0.005 | D29: 0,005 heisst ein halbes Prozent pro Jahr aus dem linearen Teil.
A30: Zinseszins je Jahr | B30: 1.005 | C30: 1.005 | D30: 1,005 heisst ein halbes Prozent pro Jahr auf das schon Erreichte. Zusammen mit dem linearen Teil ergibt das knapp ein Prozent, mit steigender Tendenz.
A31: Alter, ab dem gezaehlt wird | B31: 18 | C31: 18 | D31: Darunter rechnet das Modell keinen Schaden. Hier faengt auch die Tabelle an.
A32: Schadensbudget eines Lebens | B32: 97 | C32: 97 | D32: Wie viele Einheiten ein Leben hergibt. 97,0 ist die Summe der Jahresfaktoren von 18 bis 87 bei der Default-Kurve, also genau ein Leben bis 88. Diese Zahl steht BEWUSST fest und wird nicht aus der Kurve gerechnet: sonst kuerzt sich die Kurve heraus und die beiden Regler darueber bewegen gar nichts. So gesehen ist das hier der Gegenspieler - steilere Kurve heisst frueheres Ende, wer das ausgleichen will, hebt das Budget mit an. Lastfreies Ende je Kurve: 0,000/1,000 = 115 - 0,005/1,005 = 88 - 0,005/1,010 = 80 - 0,010/1,010 = 75.
A33: 5. Vom Score zum Schadensmultiplikator
A34: M = (Bezugsscore / Score) hoch Schaerfe. Das ist die Bruecke zwischen den beiden Zahlen: der Score sagt, wie hart gefahren wird, M sagt, um welchen Faktor das die Lebensuhr schneller laufen laesst. Weil das Endalter aus GENAU diesem Score kommt, koennen die beiden nicht mehr auseinanderlaufen - jede Verschlechterung im Score zieht das Endalter nach unten, jede Verbesserung schiebt es nach oben.
A35: Stufe oder Groesse | B35: Wert | C35: Default | D35: Bedeutung
A36: Bezugsscore (M = 1,00) | B36: 80 | C36: 80 | D36: Bei diesem Score laeuft die Uhr normal. 80 ist der Durchschnitt: gesunde Anlage, nichts gemessen, Natty oder TRT, keine Orale. Daraus ergibt sich auch der Basisindex 0,20, gegen den jedes System gerechnet wird.
A37: Restspielraum bei Index 1 | B37: 0.05 | C37: 0.05 | D37: Ein System auf Index 1,00 waere unendlich schaedlich. Dieser Rest deckelt das: 0,05 heisst, der schlimmstmoegliche Einzelfaktor ist 16 hoch Schaerfe.
A38: Schaerfe | B38: 1.15 | C38: 1.15 | D38: Wie hart ein belastetes System durchschlaegt. 1,00 waere proportional. Je hoeher, desto mehr entscheidet das schwaechste Glied und desto weniger der gesunde Rest. Kalibriert auf 1 g Dauerblast plus Trenbolon plus Methandienon, 15 Jahre ab 30 - das landet damit bei rund 61.
A39: Stapelung von Schaden auf einem System | B39: 1.5 | C39: 1.5 | D39: Zwei boese Stoffe auf demselben System sind mehr als die Summe der beiden. Der Lastfaktor geht als last hoch diesem Wert in die Saettigung. Bei 1,00 bleibt ein dreifach getroffenes System bei Index 0,70 stehen und das schwaechste Glied kommt nie richtig zum Tragen; ueber 2,00 laeuft es in die 1 und dann sind Oxandrolon und Oxymetholon gleich schlimm.
A40: Gewicht des schwaechsten Glieds | B40: 1 | C40: 1 | D40: Wie die fuenfzehn Systemgefahren zusammengefasst werden. 1,00 ist das gewichtete Mittel - schon damit dominiert ein System am Anschlag, weil die Kurve nach oben wegzieht. Hoeher heisst reiner Kettenbruch: bei 3,00 zaehlt praktisch nur noch das schlimmste System, der Rest verschwindet.
A41: 6. Blutwerte: Belastungsindex je Band
A42: Was ein gemessener Wert fuer die Belastung dieser Kategorie bedeutet. 0 heisst keine Belastung, 1 heisst volle Belastung.
A43: Stufe oder Groesse | B43: Wert | C43: Default | D43: Bedeutung
A44: Band 1 (gut) | B44: 0 | C44: 0 | D44: Im Zielbereich.
A45: Band 2 | B45: 0.4 | C45: 0.4 | D45: Leicht daneben.
A46: Band 3 | B46: 0.75 | C46: 0.75 | D46: Deutlich daneben.
A47: Band 4 (Endlevel) | B47: 1 | C47: 1 | D47: Gefahrenbereich - hier zaehlt die Messung zu 100 Prozent und die Anlage gar nicht mehr.
A48: 7. Blutwerte: wie viel eine Massnahme dort noch bringt
A49: Steht der Wert im gruenen Band, gibt es nichts mehr zu holen. Diese Stufen daempfen GEPLANTE Massnahmen, die an diesen Messwert gekoppelt sind. Schaedliche Wirkungen werden nie gedaempft.
A50: Stufe oder Groesse | B50: Wert | C50: Default | D50: Bedeutung
A51: Band 1 (gut) | B51: 0 | C51: 0 | D51: Nichts zu holen - ein Statin bei LDL 1,5 senkt keinen Schaden mehr.
A52: Band 2 | B52: 0.4 | C52: 0.4 | D52: Wenig zu holen.
A53: Band 3 | B53: 0.75 | C53: 0.75 | D53: Viel zu holen.
A54: Band 4 (Endlevel) | B54: 1 | C54: 1 | D54: Volle Wirkung - hier bringt die Massnahme am meisten.
A55: 8. Gewichtung und Aufschlaege
A56: Stufe oder Groesse | B56: Wert | C56: Default | D56: Bedeutung
A57: Gewicht der Messung gegenueber der Anlage | B57: 0.75 | C57: 0.75 | D57: 0,75 heisst: ein eingetragener Blutwert bestimmt drei Viertel der Belastung dieser Kategorie, die Genetik ein Viertel. Nicht 1,00, weil eine einzelne Messung eine Momentaufnahme ist. Im Endlevel gilt trotzdem 1,00.
A58: Load-Anteil in GEMESSENEN Kategorien | B58: 0.25 | C58: 0.25 | D58: Auch wo ein Blutwert vorliegt, wirkt ein Teil des Loads weiter. Ein normales LDL bei 1 g heisst nicht, dass an der Gefaesswand nichts passiert. Auf 0 gesetzt zaehlt in gemessenen Kategorien nur noch der Messwert.
A59: Aufschlag je Wert im Endlevel | B59: 4 | C59: 4 | D59: Punkte, die ein Wert im vierten Band zusaetzlich kostet. Laesst sich nicht wegplanen - er verschwindet erst, wenn oben ein besserer Wert steht.
A60: Oral-Abzug im DNA-Bericht: Sockel | B60: 6 | C60: 6 | D60: Gilt NUR fuer die Uebersicht des DNA-Berichts, wo steht, wie die Leber genetisch auf 17-alpha-alkylierte Substanzen reagiert. Im Stack-Planer haben die Oralen keinen Sammelabzug mehr, sondern stehen einzeln in der Substanzliste.
A61: Oral-Abzug im DNA-Bericht: Spanne | B61: 8 | C61: 8 | D61: Kommt dort oben drauf, skaliert mit der Leber-Genetik.
A62: 9. Load-Empfindlichkeit je Kategorie
A63: Wie stark eine Kategorie ueberhaupt auf die Dosis reagiert. 1,00 = voll, 0,50 = halb, 0,00 = gar nicht. Lp(a) ist genetisch festgelegt und ruehrt sich unter keiner Dosis, die Aortenwand ist strukturell.
A64: Stufe oder Groesse | B64: Wert | C64: Default | D64: Bedeutung
A65: Blutdruck/RAAS | B65: 1 | C65: 1 | D65: Reagiert direkt auf die Dosis.
A66: Blutfette-HDL | B66: 1 | C66: 1 | D66: Reagiert direkt auf die Dosis.
A67: Blutfette-LDL | B67: 1 | C67: 1 | D67: Reagiert direkt auf die Dosis.
A68: Blutfette-TG | B68: 1 | C68: 1 | D68: Reagiert direkt auf die Dosis.
A69: Glukosestoffwechsel | B69: 1 | C69: 1 | D69: Reagiert direkt auf die Dosis.
A70: Haematokrit/Blutdicke | B70: 1 | C70: 1 | D70: Reagiert direkt auf die Dosis.
A71: Herzmuskel/Hypertrophie | B71: 1 | C71: 1 | D71: Reagiert direkt auf die Dosis.
A72: Leber allgemein | B72: 1 | C72: 1 | D72: Reagiert direkt auf die Dosis.
A73: Psyche | B73: 1 | C73: 1 | D73: Reagiert direkt auf die Dosis.
A74: Thrombose/Blutgerinnung | B74: 1 | C74: 1 | D74: Reagiert direkt auf die Dosis.
A75: Aromatase/E2 | B75: 0.5 | C75: 0.5 | D75: Reagiert abgeschwaecht.
A76: Gefaesse/Atherosklerose | B76: 0.5 | C76: 0.5 | D76: Reagiert abgeschwaecht.
... A80: Blutfette-Lp(a) | B80: 0 | C80: 0 | D80: Reagiert nicht auf die Dosis.
A85: Systeme - wo die Kette reisst
A86: 16 Systeme, jedes fuer sich gerechnet. Von links nach rechts: was die Angaben oben (Dosis, Blutwert) fuer dieses System bedeuten, was der Stack an Last drauflegt und was er an Schutz zurueckholt, der Endindex daraus - und daraus der Gefahrenfaktor dieses einen Systems. Last und Schutz stehen getrennt, weil sie verschieden wirken: Last frisst den gesunden Rest und saettigt (Endindex = 1 - (1 - Index) hoch Last), Schutz nimmt einen Anteil vom Schaden weg (mal Schutzfaktor). Ohne diese Trennung lief der Schaden in den Deckel bei 1 und ab dort waren Oxandrolon und Methandienon gleich schlimm. Erst danach wird zusammengefasst, und genau das ist der Unterschied zur frueheren Fassung: dort wurden die Maluspunkte aller Systeme addiert, weshalb ein gutes LDL einen zerstoerten Herzmuskel aufwiegen konnte. Weil die Gefahrenkurve nach oben wegzieht, geht das jetzt nicht mehr - ein System am Anschlag treibt die Uhr, auch wenn alles andere gruen ist. Sind alle Systeme gleich belastet, kommt genau dasselbe heraus wie vorher. Nichts hier eintragen; alles kommt aus dem Stack-Planer.
A88: Aufschlag aus Endlevel-Werten | D88: =((Parameter!$B$36/100)/MAX(Parameter!$B$37,(Parameter!$B$36/100)-(Parameter!$B$59*SUM('Stack-Planer'!$G$93:$V$93))/100))^Parameter!$B$38 | E88: Punkte, die an keinem einzelnen System haengen, ueber dieselbe Kurve umgerechnet.
A89: Schadensmultiplikator jetzt | D89: =SUM(K$97:K$112)^(1/Parameter!$B$40)*$D$88 | E89: Gewichtetes Mittel der Gefahrenfaktoren, mal Aufschlag.
A90: Schadensmultiplikator nach den Massnahmen | D90: =SUM(L$97:L$112)^(1/Parameter!$B$40)*$D$88
A91: Punkte jetzt | D91: =MAX(0,MIN(100,Parameter!$B$36/$D$89^(1/Parameter!$B$38))) | E91: Dieselbe Skala wie bisher: 80.0 Punkte heisst Multiplikator 1,00.
A92: Punkte nach den Massnahmen | D92: =MAX(0,MIN(100,Parameter!$B$36/$D$90^(1/Parameter!$B$38)))
A93: schwaechstes Glied | D93: =INDEX($A$97:$A$112,MATCH(MAX($H$97:$H$112),$H$97:$H$112,0))&" - "&TEXT(MAX($H$97:$H$112),"0%")&" vom Tempo"
A96: System | B96: Gewicht | C96: Index aus Load und Blutwert | D96: Stack: Last | E96: Stack: Schutz | F96: Endindex jetzt | G96: Gefahr jetzt | H96: Anteil am Tempo | I96: Endindex nach Massnahmen | J96: Gefahr nach
A97: Haematokrit/Blutdicke | B97: 8.3333333 | C97: ='Stack-Planer'!G95 | D97: ='Stack-Planer'!G209 | E97: ='Stack-Planer'!G174 | F97: ='Stack-Planer'!G325 | G97: =((Parameter!$B$36/100)/MAX(Parameter!$B$37,1-F97))^Parameter!$B$38 | H97: =B97*G97/SUMPRODUCT($B$97:$B$112,$G$97:$G$112) | I97: ='Stack-Planer'!G326 | J97: =((Parameter!$B$36/100)/MAX(Parameter!$B$37,1-I97))^Parameter!$B$38 | K97: =B97/100*G97^Parameter!$B$40 | L97: =B97/100*J97^Parameter!$B$40
A98: Blutfette-HDL | B98: 8.3333333 | C98: ='Stack-Planer'!H95 | D98: ='Stack-Planer'!H209 | E98: ='Stack-Planer'!H174 | F98: ='Stack-Planer'!H325 | G98: =((Parameter!$B$36/100)/MAX(Parameter!$B$37,1-F98))^Parameter!$B$38 | H98: =B98*G98/SUMPRODUCT($B$97:$B$112,$G$97:$G$112) | I98: ='Stack-Planer'!H326 | J98: =((Parameter!$B$36/100)/MAX(Parameter!$B$37,1-I98))^Parameter!$B$38 | K98: =B98/100*G98^Parameter!$B$40 | L98: =B98/100*J98^Parameter!$B$40
A99: Blutfette-LDL | B99: 8.3333333 | C99: ='Stack-Planer'!I95 | D99: ='Stack-Planer'!I209 | E99: ='Stack-Planer'!I174 | F99: ='Stack-Planer'!I325 | G99: =((Parameter!$B$36/100)/MAX(Parameter!$B$37,1-F99))^Parameter!$B$38 | H99: =B99*G99/SUMPRODUCT($B$97:$B$112,$G$97:$G$112) | I99: ='Stack-Planer'!I326 | J99: =((Parameter!$B$36/100)/MAX(Parameter!$B$37,1-I99))^Parameter!$B$38 | K99: =B99/100*G99^Parameter!$B$40 | L99: =B99/100*J99^Parameter!$B$40
A100: Blutdruck/RAAS | B100: 8.3333333 | C100: ='Stack-Planer'!J95 | D100: ='Stack-Planer'!J209 | E100: ='Stack-Planer'!J174 | F100: ='Stack-Planer'!J325 | G100: =((Parameter!$B$36/100)/MAX(Parameter!$B$37,1-F100))^Parameter!$B$38 | H100: =B100*G100/SUMPRODUCT($B$97:$B$112,$G$97:$G$112) | I100: ='Stack-Planer'!J326 | J100: =((Parameter!$B$36/100)/MAX(Parameter!$B$37,1-I100))^Parameter!$B$38 | K100: =B100/100*G100^Parameter!$B$40 | L100: =B100/100*J100^Parameter!$B$40
A101: Herzmuskel/Hypertrophie | B101: 8.3333333 | C101: ='Stack-Planer'!K95 | D101: ='Stack-Planer'!K209 | E101: ='Stack-Planer'!K174 | F101: ='Stack-Planer'!K325 | G101: =((Parameter!$B$36/100)/MAX(Parameter!$B$37,1-F101))^Parameter!$B$38 | H101: =B101*G101/SUMPRODUCT($B$97:$B$112,$G$97:$G$112) | I101: ='Stack-Planer'!K326 | J101: =((Parameter!$B$36/100)/MAX(Parameter!$B$37,1-I101))^Parameter!$B$38 | K101: =B101/100*G101^Parameter!$B$40 | L101: =B101/100*J101^Parameter!$B$40
A102: Gefaesse/Atherosklerose | B102: 8.3333333 | C102: ='Stack-Planer'!L95 | D102: ='Stack-Planer'!L209 | E102: ='Stack-Planer'!L174 | F102: ='Stack-Planer'!L325 | G102: =((Parameter!$B$36/100)/MAX(Parameter!$B$37,1-F102))^Parameter!$B$38 | H102: =B102*G102/SUMPRODUCT($B$97:$B$112,$G$97:$G$112) | I102: ='Stack-Planer'!L326 | J102: =((Parameter!$B$36/100)/MAX(Parameter!$B$37,1-I102))^Parameter!$B$38 | K102: =B102/100*G102^Parameter!$B$40 | L102: =B102/100*J102^Parameter!$B$40
A103: Thrombose/Blutgerinnung | B103: 8.3333333 | C103: ='Stack-Planer'!M95 | D103: ='Stack-Planer'!M209 | E103: ='Stack-Planer'!M174 | F103: ='Stack-Planer'!M325 | G103: =((Parameter!$B$36/100)/MAX(Parameter!$B$37,1-F103))^Parameter!$B$38 | H103: =B103*G103/SUMPRODUCT($B$97:$B$112,$G$97:$G$112) | I103: ='Stack-Planer'!M326 | J103: =((Parameter!$B$36/100)/MAX(Parameter!$B$37,1-I103))^Parameter!$B$38 | K103: =B103/100*G103^Parameter!$B$40 | L103: =B103/100*J103^Parameter!$B$40
A104: Psyche | B104: 8.3333333 | C104: ='Stack-Planer'!N95 | D104: ='Stack-Planer'!N209 | E104: ='Stack-Planer'!N174 | F104: ='Stack-Planer'!N325 | G104: =((Parameter!$B$36/100)/MAX(Parameter!$B$37,1-F104))^Parameter!$B$38 | H104: =B104*G104/SUMPRODUCT($B$97:$B$112,$G$97:$G$112) | I104: ='Stack-Planer'!N326 | J104: =((Parameter!$B$36/100)/MAX(Parameter!$B$37,1-I104))^Parameter!$B$38 | K104: =B104/100*G104^Parameter!$B$40 | L104: =B104/100*J104^Parameter!$B$40
A105: Gefaesswand/Aorta/Lunge | B105: 8.3333333 | C105: ='Stack-Planer'!O95 | D105: ='Stack-Planer'!O209 | E105: ='Stack-Planer'!O174 | F105: ='Stack-Planer'!O325 | G105: =((Parameter!$B$36/100)/MAX(Parameter!$B$37,1-F105))^Parameter!$B$38 | H105: =B105*G105/SUMPRODUCT($B$97:$B$112,$G$97:$G$112) | I105: ='Stack-Planer'!O326 | J105: =((Parameter!$B$36/100)/MAX(Parameter!$B$37,1-I105))^Parameter!$B$38 | K105: =B105/100*G105^Parameter!$B$40 | L105: =B105/100*J105^Parameter!$B$40
A106: Blutfette-TG | B106: 4.1666667 | C106: ='Stack-Planer'!P95 | D106: ='Stack-Planer'!P209 | E106: ='Stack-Planer'!P174 | F106: ='Stack-Planer'!P325 | G106: =((Parameter!$B$36/100)/MAX(Parameter!$B$37,1-F106))^Parameter!$B$38 | H106: =B106*G106/SUMPRODUCT($B$97:$B$112,$G$97:$G$112) | I106: ='Stack-Planer'!P326 | J106: =((Parameter!$B$36/100)/MAX(Parameter!$B$37,1-I106))^Parameter!$B$38 | K106: =B106/100*G106^Parameter!$B$40 | L106: =B106/100*J106^Parameter!$B$40
A107: Herzrhythmus | B107: 4.1666667 | C107: ='Stack-Planer'!Q95 | D107: ='Stack-Planer'!Q209 | E107: ='Stack-Planer'!Q174 | F107: ='Stack-Planer'!Q325 | G107: =((Parameter!$B$36/100)/MAX(Parameter!$B$37,1-F107))^Parameter!$B$38 | H107: =B107*G107/SUMPRODUCT($B$97:$B$112,$G$97:$G$112) | I107: ='Stack-Planer'!Q326 | J107: =((Parameter!$B$36/100)/MAX(Parameter!$B$37,1-I107))^Parameter!$B$38 | K107: =B107/100*G107^Parameter!$B$40 | L107: =B107/100*J107^Parameter!$B$40
A108: Nierenfunktion | B108: 4.1666667 | C108: ='Stack-Planer'!R95 | D108: ='Stack-Planer'!R209 | E108: ='Stack-Planer'!R174 | F108: ='Stack-Planer'!R325 | G108: =((Parameter!$B$36/100)/MAX(Parameter!$B$37,1-F108))^Parameter!$B$38 | H108: =B108*G108/SUMPRODUCT($B$97:$B$112,$G$97:$G$112) | I108: ='Stack-Planer'!R326 | J108: =((Parameter!$B$36/100)/MAX(Parameter!$B$37,1-I108))^Parameter!$B$38 | K108: =B108/100*G108^Parameter!$B$40 | L108: =B108/100*J108^Parameter!$B$40
A109: Leber allgemein | B109: 4.1666667 | C109: ='Stack-Planer'!S95 | D109: ='Stack-Planer'!S209 | E109: ='Stack-Planer'!S174 | F109: ='Stack-Planer'!S325 | G109: =((Parameter!$B$36/100)/MAX(Parameter!$B$37,1-F109))^Parameter!$B$38 | H109: =B109*G109/SUMPRODUCT($B$97:$B$112,$G$97:$G$112) | I109: ='Stack-Planer'!S326 | J109: =((Parameter!$B$36/100)/MAX(Parameter!$B$37,1-I109))^Parameter!$B$38 | K109: =B109/100*G109^Parameter!$B$40 | L109: =B109/100*J109^Parameter!$B$40
A110: Glukosestoffwechsel | B110: 4.1666667 | C110: ='Stack-Planer'!T95 | D110: ='Stack-Planer'!T209 | E110: ='Stack-Planer'!T174 | F110: ='Stack-Planer'!T325 | G110: =((Parameter!$B$36/100)/MAX(Parameter!$B$37,1-F110))^Parameter!$B$38 | H110: =B110*G110/SUMPRODUCT($B$97:$B$112,$G$97:$G$112) | I110: ='Stack-Planer'!T326 | J110: =((Parameter!$B$36/100)/MAX(Parameter!$B$37,1-I110))^Parameter!$B$38 | K110: =B110/100*G110^Parameter!$B$40 | L110: =B110/100*J110^Parameter!$B$40
A111: Blutfette-Lp(a) | B111: 2.0833333 | C111: ='Stack-Planer'!U95 | D111: ='Stack-Planer'!U209 | E111: ='Stack-Planer'!U174 | F111: ='Stack-Planer'!U325 | G111: =((Parameter!$B$36/100)/MAX(Parameter!$B$37,1-F111))^Parameter!$B$38 | H111: =B111*G111/SUMPRODUCT($B$97:$B$112,$G$97:$G$112) | I111: ='Stack-Planer'!U326 | J111: =((Parameter!$B$36/100)/MAX(Parameter!$B$37,1-I111))^Parameter!$B$38 | K111: =B111/100*G111^Parameter!$B$40 | L111: =B111/100*J111^Parameter!$B$40
...
